{"type":"FeatureCollection","features":[{"type":"Feature","properties":{"ZIP":"N3H4Z9","VERTICES":14},"geometry":{"type":"Point","coordinates":[-80.37629799999999,43.395381]}},{"type":"Feature","properties":{"ZIP":"N3H5A6","VERTICES":14},"geometry":{"type":"Point","coordinates":[-80.327147,43.3916675]}},{"type":"Feature","properties":{"ZIP":"N3H4R6","VERTICES":13},"geometry":{"type":"Point","coordinates":[-80.3907695,43.4345445]}},{"type":"Feature","properties":{"ZIP":"N3H2R6","VERTICES":13},"geometry":{"type":"Point","coordinates":[-80.3376685,43.390080499999996]}},{"type":"Feature","properties":{"ZIP":"N3H5E6","VERTICES":12},"geometry":{"type":"Point","coordinates":[-80.335726,43.3987155]}},{"type":"Feature","properties":{"ZIP":"N3H4X5","VERTICES":12},"geometry":{"type":"Point","coordinates":[-80.3762935,43.395985499999995]}},{"type":"Feature","properties":{"ZIP":"N3H4X7","VERTICES":12},"geometry":{"type":"Point","coordinates":[-80.37663950000001,43.3965655]}},{"type":"Feature","properties":{"ZIP":"N3H5C3","VERTICES":12},"geometry":{"type":"Point","coordinates":[-80.3766895,43.3927705]}},{"type":"Feature","properties":{"ZIP":"N3H2G3","VERTICES":12},"geometry":{"type":"Point","coordinates":[-80.357225,43.3882755]}},{"type":"Feature","properties":{"ZIP":"N3H5R1","VERTICES":11},"geometry":{"type":"Point","coordinates":[-80.336705,43.4044665]}},{"type":"Feature","properties":{"ZIP":"N3H5L1","VERTICES":11},"geometry":{"type":"Point","coordinates":[-80.3507955,43.3926015]}},{"type":"Feature","properties":{"ZIP":"N3H3E9","VERTICES":11},"geometry":{"type":"Point","coordinates":[-80.356001,43.3920005]}},{"type":"Feature","properties":{"ZIP":"N3H5R5","VERTICES":11},"geometry":{"type":"Point","coordinates":[-80.3425455,43.403195]}},{"type":"Feature","properties":{"ZIP":"N3H4Y5","VERTICES":11},"geometry":{"type":"Point","coordinates":[-80.3377515,43.400704]}},{"type":"Feature","properties":{"ZIP":"N3H2G6","VERTICES":11},"geometry":{"type":"Point","coordinates":[-80.3575495,43.387141]}},{"type":"Feature","properties":{"ZIP":"N3H4X4","VERTICES":11},"geometry":{"type":"Point","coordinates":[-80.376353,43.396719]}},{"type":"Feature","properties":{"ZIP":"N3H2N6","VERTICES":11},"geometry":{"type":"Point","coordinates":[-80.33944199999999,43.398984]}},{"type":"Feature","properties":{"ZIP":"N3H5S3","VERTICES":11},"geometry":{"type":"Point","coordinates":[-80.3355,43.401236]}},{"type":"Feature","properties":{"ZIP":"N3H4N6","VERTICES":11},"geometry":{"type":"Point","coordinates":[-80.3397475,43.396777]}},{"type":"Feature","properties":{"ZIP":"N3H2Y1","VERTICES":11},"geometry":{"type":"Point","coordinates":[-80.3537055,43.3890615]}},{"type":"Feature","properties":{"ZIP":"N3H5P5","VERTICES":11},"geometry":{"type":"Point","coordinates":[-80.34313850000001,43.405024999999995]}},{"type":"Feature","properties":{"ZIP":"N3H5S5","VERTICES":11},"geometry":{"type":"Point","coordinates":[-80.3391685,43.4020615]}},{"type":"Feature","properties":{"ZIP":"N3H1J3","VERTICES":11},"geometry":{"type":"Point","coordinates":[-80.37336350000001,43.395070000000004]}},{"type":"Feature","properties":{"ZIP":"N3H1A6","VERTICES":11},"geometry":{"type":"Point","coordinates":[-80.373206,43.4020165]}},{"type":"Feature","properties":{"ZIP":"N3H2E1","VERTICES":11},"geometry":{"type":"Point","coordinates":[-80.35695050000001,43.3877475]}},{"type":"Feature","properties":{"ZIP":"N3H4R5","VERTICES":10},"geometry":{"type":"Point","coordinates":[-80.33027,43.389954]}},{"type":"Feature","properties":{"ZIP":"N3H5J4","VERTICES":10},"geometry":{"type":"Point","coordinates":[-80.3766825,43.3919705]}},{"type":"Feature","properties":{"ZIP":"N3H5A9","VERTICES":10},"geometry":{"type":"Point","coordinates":[-80.34751800000001,43.406298500000005]}},{"type":"Feature","properties":{"ZIP":"N3H2R1","VERTICES":10},"geometry":{"type":"Point","coordinates":[-80.3385285,43.3962665]}},{"type":"Feature","properties":{"ZIP":"N3H4P3","VERTICES":10},"geometry":{"type":"Point","coordinates":[-80.341508,43.400071]}},{"type":"Feature","properties":{"ZIP":"N3H2E2","VERTICES":10},"geometry":{"type":"Point","coordinates":[-80.3570685,43.387733]}},{"type":"Feature","properties":{"ZIP":"N3H4L9","VERTICES":10},"geometry":{"type":"Point","coordinates":[-80.3428875,43.390765]}},{"type":"Feature","properties":{"ZIP":"N3H2V2","VERTICES":10},"geometry":{"type":"Point","coordinates":[-80.3638435,43.387772]}},{"type":"Feature","properties":{"ZIP":"N3H3K8","VERTICES":10},"geometry":{"type":"Point","coordinates":[-80.3554115,43.393002499999994]}},{"type":"Feature","properties":{"ZIP":"N3H3K9","VERTICES":10},"geometry":{"type":"Point","coordinates":[-80.3531285,43.391859]}},{"type":"Feature","properties":{"ZIP":"N3H5J9","VERTICES":10},"geometry":{"type":"Point","coordinates":[-80.37758099999999,43.393982]}},{"type":"Feature","properties":{"ZIP":"N3H5S4","VERTICES":10},"geometry":{"type":"Point","coordinates":[-80.3395605,43.4026165]}},{"type":"Feature","properties":{"ZIP":"N3H5C1","VERTICES":10},"geometry":{"type":"Point","coordinates":[-80.37715449999999,43.3948755]}},{"type":"Feature","properties":{"ZIP":"N3H3Y7","VERTICES":10},"geometry":{"type":"Point","coordinates":[-80.35445899999999,43.399827]}},{"type":"Feature","properties":{"ZIP":"N3H3L3","VERTICES":10},"geometry":{"type":"Point","coordinates":[-80.35091750000001,43.390771]}},{"type":"Feature","properties":{"ZIP":"N3H4J9","VERTICES":10},"geometry":{"type":"Point","coordinates":[-80.3468845,43.396473]}},{"type":"Feature","properties":{"ZIP":"N3H5C2","VERTICES":10},"geometry":{"type":"Point","coordinates":[-80.3771555,43.394874]}},{"type":"Feature","properties":{"ZIP":"N3H2T3","VERTICES":10},"geometry":{"type":"Point","coordinates":[-80.33989600000001,43.3878725]}},{"type":"Feature","properties":{"ZIP":"N3H2Y3","VERTICES":10},"geometry":{"type":"Point","coordinates":[-80.353981,43.3880915]}},{"type":"Feature","properties":{"ZIP":"N3H4Y1","VERTICES":10},"geometry":{"type":"Point","coordinates":[-80.37743950000001,43.3986715]}},{"type":"Feature","properties":{"ZIP":"N3H4E1","VERTICES":10},"geometry":{"type":"Point","coordinates":[-80.34932549999999,43.400209000000004]}},{"type":"Feature","properties":{"ZIP":"N3H1C7","VERTICES":10},"geometry":{"type":"Point","coordinates":[-80.34843000000001,43.4035265]}},{"type":"Feature","properties":{"ZIP":"N3H4Y2","VERTICES":10},"geometry":{"type":"Point","coordinates":[-80.3774385,43.398671]}},{"type":"Feature","properties":{"ZIP":"N3H5C4","VERTICES":10},"geometry":{"type":"Point","coordinates":[-80.3766205,43.394305]}},{"type":"Feature","properties":{"ZIP":"N3H4R4","VERTICES":10},"geometry":{"type":"Point","coordinates":[-80.3302705,43.389954]}},{"type":"Feature","properties":{"ZIP":"N3H4Y3","VERTICES":10},"geometry":{"type":"Point","coordinates":[-80.3770505,43.3955395]}},{"type":"Feature","properties":{"ZIP":"N3H4X1","VERTICES":9},"geometry":{"type":"Point","coordinates":[-80.34500349999999,43.392354499999996]}},{"type":"Feature","properties":{"ZIP":"N3H4K4","VERTICES":9},"geometry":{"type":"Point","coordinates":[-80.3449905,43.393213]}},{"type":"Feature","properties":{"ZIP":"N3H2S5","VERTICES":9},"geometry":{"type":"Point","coordinates":[-80.333331,43.3889835]}},{"type":"Feature","properties":{"ZIP":"N3H4L8","VERTICES":9},"geometry":{"type":"Point","coordinates":[-80.3437625,43.393384]}},{"type":"Feature","properties":{"ZIP":"N3H2N4","VERTICES":9},"geometry":{"type":"Point","coordinates":[-80.3406555,43.398769]}},{"type":"Feature","properties":{"ZIP":"N3H4N2","VERTICES":9},"geometry":{"type":"Point","coordinates":[-80.34143,43.394211]}},{"type":"Feature","properties":{"ZIP":"N3H5T2","VERTICES":9},"geometry":{"type":"Point","coordinates":[-80.335948,43.404843]}},{"type":"Feature","properties":{"ZIP":"N3H1H3","VERTICES":9},"geometry":{"type":"Point","coordinates":[-80.3737755,43.4007635]}},{"type":"Feature","properties":{"ZIP":"N3H5L7","VERTICES":9},"geometry":{"type":"Point","coordinates":[-80.35271399999999,43.3942775]}},{"type":"Feature","properties":{"ZIP":"N3H2R4","VERTICES":9},"geometry":{"type":"Point","coordinates":[-80.34077500000001,43.39107]}},{"type":"Feature","properties":{"ZIP":"N3H3G3","VERTICES":9},"geometry":{"type":"Point","coordinates":[-80.35235750000001,43.3901815]}},{"type":"Feature","properties":{"ZIP":"N3H1B1","VERTICES":9},"geometry":{"type":"Point","coordinates":[-80.34909300000001,43.4054835]}},{"type":"Feature","properties":{"ZIP":"N3H2S7","VERTICES":9},"geometry":{"type":"Point","coordinates":[-80.337676,43.3881595]}},{"type":"Feature","properties":{"ZIP":"N3H4M1","VERTICES":9},"geometry":{"type":"Point","coordinates":[-80.34260900000001,43.3899145]}},{"type":"Feature","properties":{"ZIP":"N3H5R7","VERTICES":9},"geometry":{"type":"Point","coordinates":[-80.34157350000001,43.402009500000005]}},{"type":"Feature","properties":{"ZIP":"N3H5A1","VERTICES":9},"geometry":{"type":"Point","coordinates":[-80.37653549999999,43.3973165]}},{"type":"Feature","properties":{"ZIP":"N3H2N8","VERTICES":9},"geometry":{"type":"Point","coordinates":[-80.3390045,43.3966845]}},{"type":"Feature","properties":{"ZIP":"N3H4N5","VERTICES":9},"geometry":{"type":"Point","coordinates":[-80.33926,43.398055]}},{"type":"Feature","properties":{"ZIP":"N3H5M4","VERTICES":9},"geometry":{"type":"Point","coordinates":[-80.3450505,43.403710000000004]}},{"type":"Feature","properties":{"ZIP":"N3H3Z7","VERTICES":9},"geometry":{"type":"Point","coordinates":[-80.35317900000001,43.400048]}},{"type":"Feature","properties":{"ZIP":"N3H5A3","VERTICES":9},"geometry":{"type":"Point","coordinates":[-80.327766,43.3905475]}},{"type":"Feature","properties":{"ZIP":"N3H5M5","VERTICES":9},"geometry":{"type":"Point","coordinates":[-80.344221,43.402631]}},{"type":"Feature","properties":{"ZIP":"N3H5H3","VERTICES":9},"geometry":{"type":"Point","coordinates":[-80.3766305,43.392773500000004]}},{"type":"Feature","properties":{"ZIP":"N3H1B4","VERTICES":9},"geometry":{"type":"Point","coordinates":[-80.3737345,43.4010005]}},{"type":"Feature","properties":{"ZIP":"N3H3C1","VERTICES":9},"geometry":{"type":"Point","coordinates":[-80.35711549999999,43.3913015]}},{"type":"Feature","properties":{"ZIP":"N3H2P1","VERTICES":9},"geometry":{"type":"Point","coordinates":[-80.3385425,43.396512]}},{"type":"Feature","properties":{"ZIP":"N3H2R8","VERTICES":9},"geometry":{"type":"Point","coordinates":[-80.338814,43.390232]}},{"type":"Feature","properties":{"ZIP":"N3H3G7","VERTICES":9},"geometry":{"type":"Point","coordinates":[-80.33973700000001,43.385305]}},{"type":"Feature","properties":{"ZIP":"N3H4G1","VERTICES":9},"geometry":{"type":"Point","coordinates":[-80.3504385,43.40212]}},{"type":"Feature","properties":{"ZIP":"N3H2T2","VERTICES":9},"geometry":{"type":"Point","coordinates":[-80.33278200000001,43.388960999999995]}},{"type":"Feature","properties":{"ZIP":"N3H2V6","VERTICES":9},"geometry":{"type":"Point","coordinates":[-80.36367,43.3883005]}},{"type":"Feature","properties":{"ZIP":"N3H4N8","VERTICES":9},"geometry":{"type":"Point","coordinates":[-80.340235,43.394079000000005]}},{"type":"Feature","properties":{"ZIP":"N3H5P7","VERTICES":9},"geometry":{"type":"Point","coordinates":[-80.3394015,43.405344]}},{"type":"Feature","properties":{"ZIP":"N3H4M7","VERTICES":9},"geometry":{"type":"Point","coordinates":[-80.341255,43.3902155]}},{"type":"Feature","properties":{"ZIP":"N3H5S6","VERTICES":9},"geometry":{"type":"Point","coordinates":[-80.338234,43.402517]}},{"type":"Feature","properties":{"ZIP":"N3H2S1","VERTICES":9},"geometry":{"type":"Point","coordinates":[-80.3384585,43.3890745]}},{"type":"Feature","properties":{"ZIP":"N3H2P8","VERTICES":9},"geometry":{"type":"Point","coordinates":[-80.3371595,43.396710999999996]}},{"type":"Feature","properties":{"ZIP":"N3H2S2","VERTICES":9},"geometry":{"type":"Point","coordinates":[-80.3385125,43.38946249999999]}},{"type":"Feature","properties":{"ZIP":"N3H2T6","VERTICES":9},"geometry":{"type":"Point","coordinates":[-80.3311645,43.3888125]}},{"type":"Feature","properties":{"ZIP":"N3H3E8","VERTICES":9},"geometry":{"type":"Point","coordinates":[-80.356761,43.392393999999996]}},{"type":"Feature","properties":{"ZIP":"N3H4P2","VERTICES":9},"geometry":{"type":"Point","coordinates":[-80.3398595,43.397521499999996]}},{"type":"Feature","properties":{"ZIP":"N3H4G5","VERTICES":8},"geometry":{"type":"Point","coordinates":[-80.34891099999999,43.3988845]}},{"type":"Feature","properties":{"ZIP":"N3H2A1","VERTICES":8},"geometry":{"type":"Point","coordinates":[-80.357891,43.389401500000005]}},{"type":"Feature","properties":{"ZIP":"N3H3P8","VERTICES":8},"geometry":{"type":"Point","coordinates":[-80.35053149999999,43.3918575]}},{"type":"Feature","properties":{"ZIP":"N3H2W2","VERTICES":8},"geometry":{"type":"Point","coordinates":[-80.3626695,43.3892285]}},{"type":"Feature","properties":{"ZIP":"N3H3S1","VERTICES":8},"geometry":{"type":"Point","coordinates":[-80.33464799999999,43.383123]}},{"type":"Feature","properties":{"ZIP":"N3H4E4","VERTICES":8},"geometry":{"type":"Point","coordinates":[-80.348111,43.401863000000006]}},{"type":"Feature","properties":{"ZIP":"N3H4Y4","VERTICES":8},"geometry":{"type":"Point","coordinates":[-80.337444,43.399341]}},{"type":"Feature","properties":{"ZIP":"N3H3H8","VERTICES":8},"geometry":{"type":"Point","coordinates":[-80.334988,43.38129549999999]}},{"type":"Feature","properties":{"ZIP":"N3H4Z7","VERTICES":8},"geometry":{"type":"Point","coordinates":[-80.327212,43.390637]}},{"type":"Feature","properties":{"ZIP":"N3H4X3","VERTICES":8},"geometry":{"type":"Point","coordinates":[-80.377594,43.3959675]}},{"type":"Feature","properties":{"ZIP":"N3H2W3","VERTICES":8},"geometry":{"type":"Point","coordinates":[-80.3626795,43.3892335]}},{"type":"Feature","properties":{"ZIP":"N3H3G1","VERTICES":8},"geometry":{"type":"Point","coordinates":[-80.353954,43.390969]}},{"type":"Feature","properties":{"ZIP":"N3H3L8","VERTICES":8},"geometry":{"type":"Point","coordinates":[-80.3471405,43.3888555]}},{"type":"Feature","properties":{"ZIP":"N3H2V1","VERTICES":8},"geometry":{"type":"Point","coordinates":[-80.3629285,43.3870795]}},{"type":"Feature","properties":{"ZIP":"N3H3K7","VERTICES":8},"geometry":{"type":"Point","coordinates":[-80.35529149999999,43.3929435]}},{"type":"Feature","properties":{"ZIP":"N3H3R1","VERTICES":8},"geometry":{"type":"Point","coordinates":[-80.348918,43.391044]}},{"type":"Feature","properties":{"ZIP":"N3H4A7","VERTICES":8},"geometry":{"type":"Point","coordinates":[-80.35299950000001,43.402038]}},{"type":"Feature","properties":{"ZIP":"N3H4K6","VERTICES":8},"geometry":{"type":"Point","coordinates":[-80.348393,43.4033695]}},{"type":"Feature","properties":{"ZIP":"N3H4P7","VERTICES":8},"geometry":{"type":"Point","coordinates":[-80.337593,43.398323000000005]}},{"type":"Feature","properties":{"ZIP":"N3H3N8","VERTICES":8},"geometry":{"type":"Point","coordinates":[-80.35785949999999,43.395601]}},{"type":"Feature","properties":{"ZIP":"N3H2R5","VERTICES":8},"geometry":{"type":"Point","coordinates":[-80.3408775,43.3910555]}},{"type":"Feature","properties":{"ZIP":"N3H3M2","VERTICES":8},"geometry":{"type":"Point","coordinates":[-80.34490249999999,43.387841]}},{"type":"Feature","properties":{"ZIP":"N3H3Y4","VERTICES":8},"geometry":{"type":"Point","coordinates":[-80.355262,43.402243]}},{"type":"Feature","properties":{"ZIP":"N3H4C3","VERTICES":8},"geometry":{"type":"Point","coordinates":[-80.35185,43.4057485]}},{"type":"Feature","properties":{"ZIP":"N3H4E7","VERTICES":8},"geometry":{"type":"Point","coordinates":[-80.350593,43.403622999999996]}},{"type":"Feature","properties":{"ZIP":"N3H1B2","VERTICES":8},"geometry":{"type":"Point","coordinates":[-80.3745815,43.401210500000005]}},{"type":"Feature","properties":{"ZIP":"N3H2S8","VERTICES":8},"geometry":{"type":"Point","coordinates":[-80.336858,43.388377500000004]}},{"type":"Feature","properties":{"ZIP":"N3H4M2","VERTICES":8},"geometry":{"type":"Point","coordinates":[-80.34317300000001,43.395920000000004]}},{"type":"Feature","properties":{"ZIP":"N3H2V3","VERTICES":8},"geometry":{"type":"Point","coordinates":[-80.363058,43.387711]}},{"type":"Feature","properties":{"ZIP":"N3H1K6","VERTICES":8},"geometry":{"type":"Point","coordinates":[-80.36230499999999,43.398075000000006]}},{"type":"Feature","properties":{"ZIP":"N3H2N9","VERTICES":8},"geometry":{"type":"Point","coordinates":[-80.3373665,43.3973745]}},{"type":"Feature","properties":{"ZIP":"N3H4J7","VERTICES":8},"geometry":{"type":"Point","coordinates":[-80.3462595,43.397332000000006]}},{"type":"Feature","properties":{"ZIP":"N3H2R7","VERTICES":8},"geometry":{"type":"Point","coordinates":[-80.34019,43.389999]}},{"type":"Feature","properties":{"ZIP":"N3H4E9","VERTICES":8},"geometry":{"type":"Point","coordinates":[-80.350464,43.402076]}},{"type":"Feature","properties":{"ZIP":"N3H3Z8","VERTICES":8},"geometry":{"type":"Point","coordinates":[-80.3532045,43.3998905]}},{"type":"Feature","properties":{"ZIP":"N3H4M4","VERTICES":8},"geometry":{"type":"Point","coordinates":[-80.3424775,43.393665]}},{"type":"Feature","properties":{"ZIP":"N3H5A4","VERTICES":8},"geometry":{"type":"Point","coordinates":[-80.32709249999999,43.3912305]}},{"type":"Feature","properties":{"ZIP":"N3H5K1","VERTICES":8},"geometry":{"type":"Point","coordinates":[-80.37668149999999,43.391971]}},{"type":"Feature","properties":{"ZIP":"N3H2V5","VERTICES":8},"geometry":{"type":"Point","coordinates":[-80.3636245,43.3883995]}},{"type":"Feature","properties":{"ZIP":"N3H1A1","VERTICES":8},"geometry":{"type":"Point","coordinates":[-80.34929500000001,43.405958]}},{"type":"Feature","properties":{"ZIP":"N3H1P1","VERTICES":8},"geometry":{"type":"Point","coordinates":[-80.36402050000001,43.394251]}},{"type":"Feature","properties":{"ZIP":"N3H4M5","VERTICES":8},"geometry":{"type":"Point","coordinates":[-80.3424445,43.393624]}},{"type":"Feature","properties":{"ZIP":"N3H3R6","VERTICES":8},"geometry":{"type":"Point","coordinates":[-80.351965,43.3920395]}},{"type":"Feature","properties":{"ZIP":"N3H2C6","VERTICES":8},"geometry":{"type":"Point","coordinates":[-80.3577705,43.3884415]}},{"type":"Feature","properties":{"ZIP":"N3H4R2","VERTICES":8},"geometry":{"type":"Point","coordinates":[-80.33166299999999,43.390869499999994]}},{"type":"Feature","properties":{"ZIP":"N3H5J1","VERTICES":8},"geometry":{"type":"Point","coordinates":[-80.3708765,43.403161]}},{"type":"Feature","properties":{"ZIP":"N3H3V8","VERTICES":8},"geometry":{"type":"Point","coordinates":[-80.349509,43.3926635]}},{"type":"Feature","properties":{"ZIP":"N3H2Z7","VERTICES":8},"geometry":{"type":"Point","coordinates":[-80.35792000000001,43.3904985]}},{"type":"Feature","properties":{"ZIP":"N3H3X7","VERTICES":8},"geometry":{"type":"Point","coordinates":[-80.3584645,43.399851]}},{"type":"Feature","properties":{"ZIP":"N3H4K1","VERTICES":8},"geometry":{"type":"Point","coordinates":[-80.348743,43.403932]}},{"type":"Feature","properties":{"ZIP":"N3H2C7","VERTICES":8},"geometry":{"type":"Point","coordinates":[-80.357391,43.388494]}},{"type":"Feature","properties":{"ZIP":"N3H4G3","VERTICES":8},"geometry":{"type":"Point","coordinates":[-80.3476435,43.3969165]}},{"type":"Feature","properties":{"ZIP":"N3H3P6","VERTICES":8},"geometry":{"type":"Point","coordinates":[-80.352118,43.392671]}},{"type":"Feature","properties":{"ZIP":"N3H4H9","VERTICES":8},"geometry":{"type":"Point","coordinates":[-80.3471635,43.4013955]}},{"type":"Feature","properties":{"ZIP":"N3H5A7","VERTICES":8},"geometry":{"type":"Point","coordinates":[-80.3270415,43.3913]}},{"type":"Feature","properties":{"ZIP":"N3H1G7","VERTICES":8},"geometry":{"type":"Point","coordinates":[-80.3537555,43.401382999999996]}},{"type":"Feature","properties":{"ZIP":"N3H3X8","VERTICES":8},"geometry":{"type":"Point","coordinates":[-80.3558945,43.4012515]}},{"type":"Feature","properties":{"ZIP":"N3H4L6","VERTICES":8},"geometry":{"type":"Point","coordinates":[-80.344783,43.396503]}},{"type":"Feature","properties":{"ZIP":"N3H4Z5","VERTICES":8},"geometry":{"type":"Point","coordinates":[-80.3775865,43.398777]}},{"type":"Feature","properties":{"ZIP":"N3H5A8","VERTICES":8},"geometry":{"type":"Point","coordinates":[-80.326315,43.3906335]}},{"type":"Feature","properties":{"ZIP":"N3H5S8","VERTICES":8},"geometry":{"type":"Point","coordinates":[-80.3352495,43.403375999999994]}},{"type":"Feature","properties":{"ZIP":"N3H3X9","VERTICES":8},"geometry":{"type":"Point","coordinates":[-80.3563675,43.4021775]}},{"type":"Feature","properties":{"ZIP":"N3H2S4","VERTICES":8},"geometry":{"type":"Point","coordinates":[-80.33333,43.3889825]}},{"type":"Feature","properties":{"ZIP":"N3H1E4","VERTICES":7},"geometry":{"type":"Point","coordinates":[-80.363471,43.398458]}},{"type":"Feature","properties":{"ZIP":"N3H2G4","VERTICES":7},"geometry":{"type":"Point","coordinates":[-80.359905,43.388818]}},{"type":"Feature","properties":{"ZIP":"N3H2N3","VERTICES":7},"geometry":{"type":"Point","coordinates":[-80.340632,43.399634]}},{"type":"Feature","properties":{"ZIP":"N3H4A5","VERTICES":7},"geometry":{"type":"Point","coordinates":[-80.3533585,43.403155999999996]}},{"type":"Feature","properties":{"ZIP":"N3H1H2","VERTICES":7},"geometry":{"type":"Point","coordinates":[-80.37371049999999,43.4003795]}},{"type":"Feature","properties":{"ZIP":"N3H1A7","VERTICES":7},"geometry":{"type":"Point","coordinates":[-80.374049,43.401796000000004]}},{"type":"Feature","properties":{"ZIP":"N3H1J6","VERTICES":7},"geometry":{"type":"Point","coordinates":[-80.365899,43.3978555]}},{"type":"Feature","properties":{"ZIP":"N3H3N6","VERTICES":7},"geometry":{"type":"Point","coordinates":[-80.35796400000001,43.392174999999995]}},{"type":"Feature","properties":{"ZIP":"N3H1T6","VERTICES":7},"geometry":{"type":"Point","coordinates":[-80.3581305,43.395976000000005]}},{"type":"Feature","properties":{"ZIP":"N3H3W6","VERTICES":7},"geometry":{"type":"Point","coordinates":[-80.35868049999999,43.398702]}},{"type":"Feature","properties":{"ZIP":"N3H4A6","VERTICES":7},"geometry":{"type":"Point","coordinates":[-80.352999,43.4020375]}},{"type":"Feature","properties":{"ZIP":"N3H4J3","VERTICES":7},"geometry":{"type":"Point","coordinates":[-80.3496545,43.40374]}},{"type":"Feature","properties":{"ZIP":"N3H2B6","VERTICES":7},"geometry":{"type":"Point","coordinates":[-80.3466365,43.399928]}},{"type":"Feature","properties":{"ZIP":"N3H1A9","VERTICES":7},"geometry":{"type":"Point","coordinates":[-80.3497775,43.40543]}},{"type":"Feature","properties":{"ZIP":"N3H2E3","VERTICES":7},"geometry":{"type":"Point","coordinates":[-80.3671155,43.392778500000006]}},{"type":"Feature","properties":{"ZIP":"N3H3V1","VERTICES":7},"geometry":{"type":"Point","coordinates":[-80.3536635,43.394763499999996]}},{"type":"Feature","properties":{"ZIP":"N3H5R6","VERTICES":7},"geometry":{"type":"Point","coordinates":[-80.34213299999999,43.402775500000004]}},{"type":"Feature","properties":{"ZIP":"N3H2N5","VERTICES":7},"geometry":{"type":"Point","coordinates":[-80.338516,43.3991475]}},{"type":"Feature","properties":{"ZIP":"N3H1H4","VERTICES":7},"geometry":{"type":"Point","coordinates":[-80.370843,43.401253999999994]}},{"type":"Feature","properties":{"ZIP":"N3H1W7","VERTICES":7},"geometry":{"type":"Point","coordinates":[-80.3570605,43.395112499999996]}},{"type":"Feature","properties":{"ZIP":"N3H2J7","VERTICES":7},"geometry":{"type":"Point","coordinates":[-80.3495315,43.3892845]}},{"type":"Feature","properties":{"ZIP":"N3H3Y3","VERTICES":7},"geometry":{"type":"Point","coordinates":[-80.354809,43.397698000000005]}},{"type":"Feature","properties":{"ZIP":"N3H4E6","VERTICES":7},"geometry":{"type":"Point","coordinates":[-80.3474295,43.4022775]}},{"type":"Feature","properties":{"ZIP":"N3H4Y6","VERTICES":7},"geometry":{"type":"Point","coordinates":[-80.33838,43.3998285]}},{"type":"Feature","properties":{"ZIP":"N3H3J2","VERTICES":7},"geometry":{"type":"Point","coordinates":[-80.364666,43.3978545]}},{"type":"Feature","properties":{"ZIP":"N3H4R8","VERTICES":7},"geometry":{"type":"Point","coordinates":[-80.3927545,43.383759]}},{"type":"Feature","properties":{"ZIP":"N3H4A8","VERTICES":7},"geometry":{"type":"Point","coordinates":[-80.352656,43.400926]}},{"type":"Feature","properties":{"ZIP":"N3H5B7","VERTICES":7},"geometry":{"type":"Point","coordinates":[-80.36910950000001,43.391644]}},{"type":"Feature","properties":{"ZIP":"N3H0A1","VERTICES":7},"geometry":{"type":"Point","coordinates":[-80.338941,43.406008]}},{"type":"Feature","properties":{"ZIP":"N3H2J9","VERTICES":7},"geometry":{"type":"Point","coordinates":[-80.348431,43.390457]}},{"type":"Feature","properties":{"ZIP":"N3H3A5","VERTICES":7},"geometry":{"type":"Point","coordinates":[-80.36661050000001,43.396232999999995]}},{"type":"Feature","properties":{"ZIP":"N3H3G4","VERTICES":7},"geometry":{"type":"Point","coordinates":[-80.352102,43.390057]}},{"type":"Feature","properties":{"ZIP":"N3H4P8","VERTICES":7},"geometry":{"type":"Point","coordinates":[-80.337673,43.398562999999996]}},{"type":"Feature","properties":{"ZIP":"N3H4Y7","VERTICES":7},"geometry":{"type":"Point","coordinates":[-80.338566,43.4005535]}},{"type":"Feature","properties":{"ZIP":"N3H3N9","VERTICES":7},"geometry":{"type":"Point","coordinates":[-80.3577035,43.395517999999996]}},{"type":"Feature","properties":{"ZIP":"N3H5J8","VERTICES":7},"geometry":{"type":"Point","coordinates":[-80.37804249999999,43.394271]}},{"type":"Feature","properties":{"ZIP":"N3H5S2","VERTICES":7},"geometry":{"type":"Point","coordinates":[-80.3359405,43.4007335]}},{"type":"Feature","properties":{"ZIP":"N3H2A6","VERTICES":7},"geometry":{"type":"Point","coordinates":[-80.3517615,43.3945565]}},{"type":"Feature","properties":{"ZIP":"N3H3E2","VERTICES":7},"geometry":{"type":"Point","coordinates":[-80.360736,43.3944825]}},{"type":"Feature","properties":{"ZIP":"N3H4X6","VERTICES":7},"geometry":{"type":"Point","coordinates":[-80.3754525,43.3968045]}},{"type":"Feature","properties":{"ZIP":"N3H1X1","VERTICES":7},"geometry":{"type":"Point","coordinates":[-80.35724049999999,43.39484]}},{"type":"Feature","properties":{"ZIP":"N3H3S7","VERTICES":7},"geometry":{"type":"Point","coordinates":[-80.336187,43.383663]}},{"type":"Feature","properties":{"ZIP":"N3H3Y5","VERTICES":7},"geometry":{"type":"Point","coordinates":[-80.35536450000001,43.402859500000005]}},{"type":"Feature","properties":{"ZIP":"N3H4C4","VERTICES":7},"geometry":{"type":"Point","coordinates":[-80.351605,43.404924]}},{"type":"Feature","properties":{"ZIP":"N3H4E8","VERTICES":7},"geometry":{"type":"Point","coordinates":[-80.350593,43.403623]}},{"type":"Feature","properties":{"ZIP":"N3H4P9","VERTICES":7},"geometry":{"type":"Point","coordinates":[-80.3306455,43.389454]}},{"type":"Feature","properties":{"ZIP":"N3H2X9","VERTICES":7},"geometry":{"type":"Point","coordinates":[-80.3550285,43.3879215]}},{"type":"Feature","properties":{"ZIP":"N3H4H2","VERTICES":7},"geometry":{"type":"Point","coordinates":[-80.3483265,43.3999285]}},{"type":"Feature","properties":{"ZIP":"N3H1E9","VERTICES":7},"geometry":{"type":"Point","coordinates":[-80.3631405,43.397911]}},{"type":"Feature","properties":{"ZIP":"N3H2A7","VERTICES":7},"geometry":{"type":"Point","coordinates":[-80.35082,43.395547]}},{"type":"Feature","properties":{"ZIP":"N3H3L1","VERTICES":7},"geometry":{"type":"Point","coordinates":[-80.3530075,43.3920265]}},{"type":"Feature","properties":{"ZIP":"N3H4B1","VERTICES":7},"geometry":{"type":"Point","coordinates":[-80.353741,43.4060205]}},{"type":"Feature","properties":{"ZIP":"N3H1H7","VERTICES":7},"geometry":{"type":"Point","coordinates":[-80.37894750000001,43.390524]}},{"type":"Feature","properties":{"ZIP":"N3H1X2","VERTICES":7},"geometry":{"type":"Point","coordinates":[-80.3599275,43.392146499999996]}},{"type":"Feature","properties":{"ZIP":"N3H2C4","VERTICES":7},"geometry":{"type":"Point","coordinates":[-80.3559145,43.3895895]}},{"type":"Feature","properties":{"ZIP":"N3H2K5","VERTICES":7},"geometry":{"type":"Point","coordinates":[-80.34119799999999,43.3921535]}},{"type":"Feature","properties":{"ZIP":"N3H1R9","VERTICES":7},"geometry":{"type":"Point","coordinates":[-80.364299,43.391906500000005]}},{"type":"Feature","properties":{"ZIP":"N3H2T1","VERTICES":7},"geometry":{"type":"Point","coordinates":[-80.331601,43.389528999999996]}},{"type":"Feature","properties":{"ZIP":"N3H3P2","VERTICES":7},"geometry":{"type":"Point","coordinates":[-80.3563375,43.3949785]}},{"type":"Feature","properties":{"ZIP":"N3H1V2","VERTICES":7},"geometry":{"type":"Point","coordinates":[-80.3648155,43.389663999999996]}},{"type":"Feature","properties":{"ZIP":"N3H3E4","VERTICES":7},"geometry":{"type":"Point","coordinates":[-80.35914500000001,43.393632999999994]}},{"type":"Feature","properties":{"ZIP":"N3H3L2","VERTICES":7},"geometry":{"type":"Point","coordinates":[-80.3514325,43.3908655]}},{"type":"Feature","properties":{"ZIP":"N3H4N7","VERTICES":7},"geometry":{"type":"Point","coordinates":[-80.34070750000001,43.3965965]}},{"type":"Feature","properties":{"ZIP":"N3H4Z2","VERTICES":7},"geometry":{"type":"Point","coordinates":[-80.33769799999999,43.4004885]}},{"type":"Feature","properties":{"ZIP":"N3H1K9","VERTICES":7},"geometry":{"type":"Point","coordinates":[-80.3624805,43.398035]}},{"type":"Feature","properties":{"ZIP":"N3H2M7","VERTICES":7},"geometry":{"type":"Point","coordinates":[-80.33674350000001,43.3834515]}},{"type":"Feature","properties":{"ZIP":"N3H3C2","VERTICES":7},"geometry":{"type":"Point","coordinates":[-80.357116,43.3913015]}},{"type":"Feature","properties":{"ZIP":"N3H4H7","VERTICES":7},"geometry":{"type":"Point","coordinates":[-80.3472575,43.400408]}},{"type":"Feature","properties":{"ZIP":"N3H5K3","VERTICES":7},"geometry":{"type":"Point","coordinates":[-80.3438355,43.391689]}},{"type":"Feature","properties":{"ZIP":"N3H2Z6","VERTICES":7},"geometry":{"type":"Point","coordinates":[-80.36040700000001,43.3917715]}},{"type":"Feature","properties":{"ZIP":"N3H1A2","VERTICES":7},"geometry":{"type":"Point","coordinates":[-80.3496515,43.4062005]}},{"type":"Feature","properties":{"ZIP":"N3H1C4","VERTICES":7},"geometry":{"type":"Point","coordinates":[-80.35212,43.402978000000004]}},{"type":"Feature","properties":{"ZIP":"N3H3C3","VERTICES":7},"geometry":{"type":"Point","coordinates":[-80.3659995,43.3970525]}},{"type":"Feature","properties":{"ZIP":"N3H4H8","VERTICES":7},"geometry":{"type":"Point","coordinates":[-80.349322,43.400715500000004]}},{"type":"Feature","properties":{"ZIP":"N3H1G6","VERTICES":7},"geometry":{"type":"Point","coordinates":[-80.354157,43.401216500000004]}},{"type":"Feature","properties":{"ZIP":"N3H2B2","VERTICES":7},"geometry":{"type":"Point","coordinates":[-80.3487455,43.397754500000005]}},{"type":"Feature","properties":{"ZIP":"N3H3E6","VERTICES":7},"geometry":{"type":"Point","coordinates":[-80.3579975,43.393035]}},{"type":"Feature","properties":{"ZIP":"N3H1P3","VERTICES":7},"geometry":{"type":"Point","coordinates":[-80.364848,43.3934155]}},{"type":"Feature","properties":{"ZIP":"N3H4Z4","VERTICES":7},"geometry":{"type":"Point","coordinates":[-80.37794650000001,43.397362]}},{"type":"Feature","properties":{"ZIP":"N3H5J2","VERTICES":7},"geometry":{"type":"Point","coordinates":[-80.3708365,43.40318]}},{"type":"Feature","properties":{"ZIP":"N3H2G2","VERTICES":7},"geometry":{"type":"Point","coordinates":[-80.36166850000001,43.389919500000005]}},{"type":"Feature","properties":{"ZIP":"N3H3C5","VERTICES":7},"geometry":{"type":"Point","coordinates":[-80.364524,43.3964425]}},{"type":"Feature","properties":{"ZIP":"N3H4M8","VERTICES":7},"geometry":{"type":"Point","coordinates":[-80.34141600000001,43.3905215]}},{"type":"Feature","properties":{"ZIP":"N3H5S7","VERTICES":7},"geometry":{"type":"Point","coordinates":[-80.3367985,43.402902499999996]}},{"type":"Feature","properties":{"ZIP":"N3H2Z8","VERTICES":7},"geometry":{"type":"Point","coordinates":[-80.358329,43.39071]}},{"type":"Feature","properties":{"ZIP":"N3H3R8","VERTICES":7},"geometry":{"type":"Point","coordinates":[-80.342896,43.3880185]}},{"type":"Feature","properties":{"ZIP":"N3H4B5","VERTICES":7},"geometry":{"type":"Point","coordinates":[-80.3522965,43.402317]}},{"type":"Feature","properties":{"ZIP":"N3H4K2","VERTICES":7},"geometry":{"type":"Point","coordinates":[-80.34871749999999,43.4038575]}},{"type":"Feature","properties":{"ZIP":"N3H3N2","VERTICES":7},"geometry":{"type":"Point","coordinates":[-80.3604075,43.396894]}},{"type":"Feature","properties":{"ZIP":"N3H3Z1","VERTICES":7},"geometry":{"type":"Point","coordinates":[-80.3535865,43.3965395]}},{"type":"Feature","properties":{"ZIP":"N3H5J3","VERTICES":7},"geometry":{"type":"Point","coordinates":[-80.371156,43.4031405]}},{"type":"Feature","properties":{"ZIP":"N3H2N2","VERTICES":7},"geometry":{"type":"Point","coordinates":[-80.3409115,43.400292500000006]}},{"type":"Feature","properties":{"ZIP":"N3H2Y7","VERTICES":7},"geometry":{"type":"Point","coordinates":[-80.365499,43.3943675]}},{"type":"Feature","properties":{"ZIP":"N3H4A4","VERTICES":7},"geometry":{"type":"Point","coordinates":[-80.3534315,43.4030945]}},{"type":"Feature","properties":{"ZIP":"N3H1N2","VERTICES":7},"geometry":{"type":"Point","coordinates":[-80.360829,43.3975045]}},{"type":"Feature","properties":{"ZIP":"N3H2W1","VERTICES":7},"geometry":{"type":"Point","coordinates":[-80.36779949999999,43.3921175]}},{"type":"Feature","properties":{"ZIP":"N3H2Z9","VERTICES":7},"geometry":{"type":"Point","coordinates":[-80.357223,43.3901105]}},{"type":"Feature","properties":{"ZIP":"N3H4B6","VERTICES":7},"geometry":{"type":"Point","coordinates":[-80.352297,43.402317]}},{"type":"Feature","properties":{"ZIP":"N3H4K3","VERTICES":7},"geometry":{"type":"Point","coordinates":[-80.345336,43.3940955]}},{"type":"Feature","properties":{"ZIP":"N3H4L7","VERTICES":6},"geometry":{"type":"Point","coordinates":[-80.343986,43.3938045]}},{"type":"Feature","properties":{"ZIP":"N3H4Z6","VERTICES":6},"geometry":{"type":"Point","coordinates":[-80.32696849999999,43.3898765]}},{"type":"Feature","properties":{"ZIP":"N3H1T5","VERTICES":6},"geometry":{"type":"Point","coordinates":[-80.3611925,43.39296]}},{"type":"Feature","properties":{"ZIP":"N3H2Y8","VERTICES":6},"geometry":{"type":"Point","coordinates":[-80.36357000000001,43.393389]}},{"type":"Feature","properties":{"ZIP":"N3H3W5","VERTICES":6},"geometry":{"type":"Point","coordinates":[-80.3599885,43.399236]}},{"type":"Feature","properties":{"ZIP":"N3H4J2","VERTICES":6},"geometry":{"type":"Point","coordinates":[-80.3496655,43.4037745]}},{"type":"Feature","properties":{"ZIP":"N3H2B5","VERTICES":6},"geometry":{"type":"Point","coordinates":[-80.34752499999999,43.399016]}},{"type":"Feature","properties":{"ZIP":"N3H3L7","VERTICES":6},"geometry":{"type":"Point","coordinates":[-80.34866450000001,43.389621500000004]}},{"type":"Feature","properties":{"ZIP":"N3H3Y1","VERTICES":6},"geometry":{"type":"Point","coordinates":[-80.3555155,43.400084500000006]}},{"type":"Feature","properties":{"ZIP":"N3H4B8","VERTICES":6},"geometry":{"type":"Point","coordinates":[-80.3515415,43.403611999999995]}},{"type":"Feature","properties":{"ZIP":"N3H1R2","VERTICES":6},"geometry":{"type":"Point","coordinates":[-80.3617335,43.3945005]}},{"type":"Feature","properties":{"ZIP":"N3H2L9","VERTICES":6},"geometry":{"type":"Point","coordinates":[-80.339805,43.385109]}},{"type":"Feature","properties":{"ZIP":"N3H4G6","VERTICES":6},"geometry":{"type":"Point","coordinates":[-80.34912650000001,43.399001]}},{"type":"Feature","properties":{"ZIP":"N3H5J5","VERTICES":6},"geometry":{"type":"Point","coordinates":[-80.37828400000001,43.392676]}},{"type":"Feature","properties":{"ZIP":"N3H1L6","VERTICES":6},"geometry":{"type":"Point","coordinates":[-80.362561,43.397724499999995]}},{"type":"Feature","properties":{"ZIP":"N3H2A2","VERTICES":6},"geometry":{"type":"Point","coordinates":[-80.35786949999999,43.390162000000004]}},{"type":"Feature","properties":{"ZIP":"N3H2T9","VERTICES":6},"geometry":{"type":"Point","coordinates":[-80.371339,43.4019385]}},{"type":"Feature","properties":{"ZIP":"N3H2Y9","VERTICES":6},"geometry":{"type":"Point","coordinates":[-80.363738,43.393474]}},{"type":"Feature","properties":{"ZIP":"N3H3C8","VERTICES":6},"geometry":{"type":"Point","coordinates":[-80.36334099999999,43.39583450000001]}},{"type":"Feature","properties":{"ZIP":"N3H3K5","VERTICES":6},"geometry":{"type":"Point","coordinates":[-80.357301,43.39388]}},{"type":"Feature","properties":{"ZIP":"N3H3P9","VERTICES":6},"geometry":{"type":"Point","coordinates":[-80.353175,43.393120499999995]}},{"type":"Feature","properties":{"ZIP":"N3H5B3","VERTICES":6},"geometry":{"type":"Point","coordinates":[-80.3452995,43.391275]}},{"type":"Feature","properties":{"ZIP":"N3H2J4","VERTICES":6},"geometry":{"type":"Point","coordinates":[-80.349118,43.391848499999995]}},{"type":"Feature","properties":{"ZIP":"N3H2R2","VERTICES":6},"geometry":{"type":"Point","coordinates":[-80.3406375,43.393983000000006]}},{"type":"Feature","properties":{"ZIP":"N3H3Y2","VERTICES":6},"geometry":{"type":"Point","coordinates":[-80.3548575,43.3978575]}},{"type":"Feature","properties":{"ZIP":"N3H4E5","VERTICES":6},"geometry":{"type":"Point","coordinates":[-80.34848,43.4015785]}},{"type":"Feature","properties":{"ZIP":"N3H4P6","VERTICES":6},"geometry":{"type":"Point","coordinates":[-80.340664,43.3993545]}},{"type":"Feature","properties":{"ZIP":"N3H1J7","VERTICES":6},"geometry":{"type":"Point","coordinates":[-80.3658985,43.397996500000005]}},{"type":"Feature","properties":{"ZIP":"N3H2S6","VERTICES":6},"geometry":{"type":"Point","coordinates":[-80.3390775,43.3882055]}},{"type":"Feature","properties":{"ZIP":"N3H2X6","VERTICES":6},"geometry":{"type":"Point","coordinates":[-80.3604735,43.390561500000004]}},{"type":"Feature","properties":{"ZIP":"N3H3H9","VERTICES":6},"geometry":{"type":"Point","coordinates":[-80.335668,43.381907]}},{"type":"Feature","properties":{"ZIP":"N3H3N7","VERTICES":6},"geometry":{"type":"Point","coordinates":[-80.3590615,43.396232]}},{"type":"Feature","properties":{"ZIP":"N3H4R7","VERTICES":6},"geometry":{"type":"Point","coordinates":[-80.3773755,43.416286]}},{"type":"Feature","properties":{"ZIP":"N3H4Z8","VERTICES":6},"geometry":{"type":"Point","coordinates":[-80.3271595,43.390553]}},{"type":"Feature","properties":{"ZIP":"N3H1E6","VERTICES":6},"geometry":{"type":"Point","coordinates":[-80.36373499999999,43.3981685]}},{"type":"Feature","properties":{"ZIP":"N3H1L8","VERTICES":6},"geometry":{"type":"Point","coordinates":[-80.3625435,43.397982]}},{"type":"Feature","properties":{"ZIP":"N3H2A3","VERTICES":6},"geometry":{"type":"Point","coordinates":[-80.3581425,43.3886715]}},{"type":"Feature","properties":{"ZIP":"N3H3C9","VERTICES":6},"geometry":{"type":"Point","coordinates":[-80.362154,43.395113]}},{"type":"Feature","properties":{"ZIP":"N3H4J4","VERTICES":6},"geometry":{"type":"Point","coordinates":[-80.34958900000001,43.403536]}},{"type":"Feature","properties":{"ZIP":"N3H4N3","VERTICES":6},"geometry":{"type":"Point","coordinates":[-80.341613,43.3946695]}},{"type":"Feature","properties":{"ZIP":"N3H5B5","VERTICES":6},"geometry":{"type":"Point","coordinates":[-80.368876,43.3916575]}},{"type":"Feature","properties":{"ZIP":"N3H5T3","VERTICES":6},"geometry":{"type":"Point","coordinates":[-80.336644,43.405705999999995]}},{"type":"Feature","properties":{"ZIP":"N3H2B7","VERTICES":6},"geometry":{"type":"Point","coordinates":[-80.34687650000001,43.39969]}},{"type":"Feature","properties":{"ZIP":"N3H2W4","VERTICES":6},"geometry":{"type":"Point","coordinates":[-80.3675685,43.394177]}},{"type":"Feature","properties":{"ZIP":"N3H5N9","VERTICES":6},"geometry":{"type":"Point","coordinates":[-80.34436149999999,43.404085]}},{"type":"Feature","properties":{"ZIP":"N3H2E4","VERTICES":6},"geometry":{"type":"Point","coordinates":[-80.3668705,43.39265]}},{"type":"Feature","properties":{"ZIP":"N3H3B7","VERTICES":6},"geometry":{"type":"Point","coordinates":[-80.360209,43.392917]}},{"type":"Feature","properties":{"ZIP":"N3H1E7","VERTICES":6},"geometry":{"type":"Point","coordinates":[-80.362851,43.39857]}},{"type":"Feature","properties":{"ZIP":"N3H1T8","VERTICES":6},"geometry":{"type":"Point","coordinates":[-80.36220399999999,43.39201]}},{"type":"Feature","properties":{"ZIP":"N3H2G7","VERTICES":6},"geometry":{"type":"Point","coordinates":[-80.347454,43.3976865]}},{"type":"Feature","properties":{"ZIP":"N3H3E1","VERTICES":6},"geometry":{"type":"Point","coordinates":[-80.3620835,43.395185999999995]}},{"type":"Feature","properties":{"ZIP":"N3H3R2","VERTICES":6},"geometry":{"type":"Point","coordinates":[-80.35219649999999,43.3924375]}},{"type":"Feature","properties":{"ZIP":"N3H3W8","VERTICES":6},"geometry":{"type":"Point","coordinates":[-80.3559515,43.3972205]}},{"type":"Feature","properties":{"ZIP":"N3H5L8","VERTICES":6},"geometry":{"type":"Point","coordinates":[-80.3285185,43.413468]}},{"type":"Feature","properties":{"ZIP":"N3H1H5","VERTICES":6},"geometry":{"type":"Point","coordinates":[-80.3709045,43.401139]}},{"type":"Feature","properties":{"ZIP":"N3H1N7","VERTICES":6},"geometry":{"type":"Point","coordinates":[-80.363186,43.395105]}},{"type":"Feature","properties":{"ZIP":"N3H1W9","VERTICES":6},"geometry":{"type":"Point","coordinates":[-80.3570395,43.3951315]}},{"type":"Feature","properties":{"ZIP":"N3H2W6","VERTICES":6},"geometry":{"type":"Point","coordinates":[-80.36610300000001,43.3934285]}},{"type":"Feature","properties":{"ZIP":"N3H3S4","VERTICES":6},"geometry":{"type":"Point","coordinates":[-80.3366375,43.3839535]}},{"type":"Feature","properties":{"ZIP":"N3H4K7","VERTICES":6},"geometry":{"type":"Point","coordinates":[-80.355032,43.402274000000006]}},{"type":"Feature","properties":{"ZIP":"N3H5G4","VERTICES":6},"geometry":{"type":"Point","coordinates":[-80.352675,43.402652]}},{"type":"Feature","properties":{"ZIP":"N3H5P1","VERTICES":6},"geometry":{"type":"Point","coordinates":[-80.35251400000001,43.3940315]}},{"type":"Feature","properties":{"ZIP":"N3H1Z1","VERTICES":6},"geometry":{"type":"Point","coordinates":[-80.3585645,43.3916765]}},{"type":"Feature","properties":{"ZIP":"N3H2M3","VERTICES":6},"geometry":{"type":"Point","coordinates":[-80.3389655,43.3845665]}},{"type":"Feature","properties":{"ZIP":"N3H3B8","VERTICES":6},"geometry":{"type":"Point","coordinates":[-80.3589915,43.392279]}},{"type":"Feature","properties":{"ZIP":"N3H3J4","VERTICES":6},"geometry":{"type":"Point","coordinates":[-80.36376849999999,43.397356]}},{"type":"Feature","properties":{"ZIP":"N3H4H1","VERTICES":6},"geometry":{"type":"Point","coordinates":[-80.34818899999999,43.399847]}},{"type":"Feature","properties":{"ZIP":"N3H4V6","VERTICES":6},"geometry":{"type":"Point","coordinates":[-80.3351505,43.393248]}},{"type":"Feature","properties":{"ZIP":"N3H1E8","VERTICES":6},"geometry":{"type":"Point","coordinates":[-80.363632,43.3979585]}},{"type":"Feature","properties":{"ZIP":"N3H1T9","VERTICES":6},"geometry":{"type":"Point","coordinates":[-80.3628295,43.391272]}},{"type":"Feature","properties":{"ZIP":"N3H2Z3","VERTICES":6},"geometry":{"type":"Point","coordinates":[-80.36101450000001,43.392082]}},{"type":"Feature","properties":{"ZIP":"N3H3R3","VERTICES":6},"geometry":{"type":"Point","coordinates":[-80.35116450000001,43.3919435]}},{"type":"Feature","properties":{"ZIP":"N3H3X1","VERTICES":6},"geometry":{"type":"Point","coordinates":[-80.3544875,43.3964625]}},{"type":"Feature","properties":{"ZIP":"N3H1N8","VERTICES":6},"geometry":{"type":"Point","coordinates":[-80.363186,43.395105]}},{"type":"Feature","properties":{"ZIP":"N3H2C1","VERTICES":6},"geometry":{"type":"Point","coordinates":[-80.35319150000001,43.3933155]}},{"type":"Feature","properties":{"ZIP":"N3H2W7","VERTICES":6},"geometry":{"type":"Point","coordinates":[-80.3658655,43.3933085]}},{"type":"Feature","properties":{"ZIP":"N3H3A7","VERTICES":6},"geometry":{"type":"Point","coordinates":[-80.3627215,43.3979075]}},{"type":"Feature","properties":{"ZIP":"N3H3M3","VERTICES":6},"geometry":{"type":"Point","coordinates":[-80.34384850000001,43.387389]}},{"type":"Feature","properties":{"ZIP":"N3H4L1","VERTICES":6},"geometry":{"type":"Point","coordinates":[-80.3454665,43.398832999999996]}},{"type":"Feature","properties":{"ZIP":"N3H4Y9","VERTICES":6},"geometry":{"type":"Point","coordinates":[-80.338682,43.40047250000001]}},{"type":"Feature","properties":{"ZIP":"N3H5G7","VERTICES":6},"geometry":{"type":"Point","coordinates":[-80.329437,43.3925505]}},{"type":"Feature","properties":{"ZIP":"N3H5P2","VERTICES":6},"geometry":{"type":"Point","coordinates":[-80.3406085,43.4044965]}},{"type":"Feature","properties":{"ZIP":"N3H2E7","VERTICES":6},"geometry":{"type":"Point","coordinates":[-80.364013,43.391141000000005]}},{"type":"Feature","properties":{"ZIP":"N3H2S9","VERTICES":6},"geometry":{"type":"Point","coordinates":[-80.331365,43.3897645]}},{"type":"Feature","properties":{"ZIP":"N3H3J6","VERTICES":6},"geometry":{"type":"Point","coordinates":[-80.36221499999999,43.3965385]}},{"type":"Feature","properties":{"ZIP":"N3H3P1","VERTICES":6},"geometry":{"type":"Point","coordinates":[-80.3564305,43.3948365]}},{"type":"Feature","properties":{"ZIP":"N3H4M3","VERTICES":6},"geometry":{"type":"Point","coordinates":[-80.343141,43.395814]}},{"type":"Feature","properties":{"ZIP":"N3H2V4","VERTICES":6},"geometry":{"type":"Point","coordinates":[-80.3617235,43.3873105]}},{"type":"Feature","properties":{"ZIP":"N3H2Z4","VERTICES":6},"geometry":{"type":"Point","coordinates":[-80.36101500000001,43.392082]}},{"type":"Feature","properties":{"ZIP":"N3H3E3","VERTICES":6},"geometry":{"type":"Point","coordinates":[-80.360736,43.3944825]}},{"type":"Feature","properties":{"ZIP":"N3H3R4","VERTICES":6},"geometry":{"type":"Point","coordinates":[-80.34773150000001,43.390438]}},{"type":"Feature","properties":{"ZIP":"N3H3A8","VERTICES":6},"geometry":{"type":"Point","coordinates":[-80.365313,43.395539]}},{"type":"Feature","properties":{"ZIP":"N3H3M6","VERTICES":6},"geometry":{"type":"Point","coordinates":[-80.3640795,43.3988585]}},{"type":"Feature","properties":{"ZIP":"N3H3S9","VERTICES":6},"geometry":{"type":"Point","coordinates":[-80.3611625,43.398548000000005]}},{"type":"Feature","properties":{"ZIP":"N3H4C5","VERTICES":6},"geometry":{"type":"Point","coordinates":[-80.3515235,43.4046515]}},{"type":"Feature","properties":{"ZIP":"N3H4Z1","VERTICES":6},"geometry":{"type":"Point","coordinates":[-80.33778699999999,43.401258999999996]}},{"type":"Feature","properties":{"ZIP":"N3H1K8","VERTICES":6},"geometry":{"type":"Point","coordinates":[-80.362083,43.398057]}},{"type":"Feature","properties":{"ZIP":"N3H1Z3","VERTICES":6},"geometry":{"type":"Point","coordinates":[-80.359317,43.390812]}},{"type":"Feature","properties":{"ZIP":"N3H2E8","VERTICES":6},"geometry":{"type":"Point","coordinates":[-80.36248850000001,43.3903495]}},{"type":"Feature","properties":{"ZIP":"N3H2M6","VERTICES":6},"geometry":{"type":"Point","coordinates":[-80.33751,43.383382]}},{"type":"Feature","properties":{"ZIP":"N3H3J8","VERTICES":6},"geometry":{"type":"Point","coordinates":[-80.36127350000001,43.3960565]}},{"type":"Feature","properties":{"ZIP":"N3H1G1","VERTICES":6},"geometry":{"type":"Point","coordinates":[-80.3621085,43.398845]}},{"type":"Feature","properties":{"ZIP":"N3H2A8","VERTICES":6},"geometry":{"type":"Point","coordinates":[-80.350479,43.395929499999994]}},{"type":"Feature","properties":{"ZIP":"N3H2Z5","VERTICES":6},"geometry":{"type":"Point","coordinates":[-80.359585,43.3913505]}},{"type":"Feature","properties":{"ZIP":"N3H3R5","VERTICES":6},"geometry":{"type":"Point","coordinates":[-80.3464185,43.389756500000004]}},{"type":"Feature","properties":{"ZIP":"N3H4B2","VERTICES":6},"geometry":{"type":"Point","coordinates":[-80.35373949999999,43.406017000000006]}},{"type":"Feature","properties":{"ZIP":"N3H4X8","VERTICES":6},"geometry":{"type":"Point","coordinates":[-80.37737150000001,43.3971935]}},{"type":"Feature","properties":{"ZIP":"N3H5M6","VERTICES":6},"geometry":{"type":"Point","coordinates":[-80.3429795,43.4018045]}},{"type":"Feature","properties":{"ZIP":"N3H1H8","VERTICES":6},"geometry":{"type":"Point","coordinates":[-80.3755625,43.3919725]}},{"type":"Feature","properties":{"ZIP":"N3H1X3","VERTICES":6},"geometry":{"type":"Point","coordinates":[-80.36005349999999,43.3921275]}},{"type":"Feature","properties":{"ZIP":"N3H2K6","VERTICES":6},"geometry":{"type":"Point","coordinates":[-80.341369,43.3921235]}},{"type":"Feature","properties":{"ZIP":"N3H2W9","VERTICES":6},"geometry":{"type":"Point","coordinates":[-80.3646255,43.392683]}},{"type":"Feature","properties":{"ZIP":"N3H3A9","VERTICES":6},"geometry":{"type":"Point","coordinates":[-80.364109,43.3949265]}},{"type":"Feature","properties":{"ZIP":"N3H3T1","VERTICES":6},"geometry":{"type":"Point","coordinates":[-80.361169,43.3984315]}},{"type":"Feature","properties":{"ZIP":"N3H4C8","VERTICES":6},"geometry":{"type":"Point","coordinates":[-80.349585,43.398157]}},{"type":"Feature","properties":{"ZIP":"N3H4L3","VERTICES":6},"geometry":{"type":"Point","coordinates":[-80.3465985,43.402302000000006]}},{"type":"Feature","properties":{"ZIP":"N3H5H9","VERTICES":6},"geometry":{"type":"Point","coordinates":[-80.355436,43.3870195]}},{"type":"Feature","properties":{"ZIP":"N3H1C3","VERTICES":6},"geometry":{"type":"Point","coordinates":[-80.3556035,43.402387000000004]}},{"type":"Feature","properties":{"ZIP":"N3H2E9","VERTICES":6},"geometry":{"type":"Point","coordinates":[-80.362636,43.390426]}},{"type":"Feature","properties":{"ZIP":"N3H3J9","VERTICES":6},"geometry":{"type":"Point","coordinates":[-80.3612545,43.396046999999996]}},{"type":"Feature","properties":{"ZIP":"N3H3Z9","VERTICES":6},"geometry":{"type":"Point","coordinates":[-80.3544435,43.403028500000005]}},{"type":"Feature","properties":{"ZIP":"N3H3E5","VERTICES":6},"geometry":{"type":"Point","coordinates":[-80.359393,43.393766]}},{"type":"Feature","properties":{"ZIP":"N3H3X6","VERTICES":6},"geometry":{"type":"Point","coordinates":[-80.359167,43.400215]}},{"type":"Feature","properties":{"ZIP":"N3H4B3","VERTICES":6},"geometry":{"type":"Point","coordinates":[-80.3526665,43.4034745]}},{"type":"Feature","properties":{"ZIP":"N3H4X9","VERTICES":6},"geometry":{"type":"Point","coordinates":[-80.3765545,43.397429]}},{"type":"Feature","properties":{"ZIP":"N3H5M7","VERTICES":6},"geometry":{"type":"Point","coordinates":[-80.3442315,43.403476999999995]}},{"type":"Feature","properties":{"ZIP":"N3H1P2","VERTICES":6},"geometry":{"type":"Point","coordinates":[-80.364848,43.3934155]}},{"type":"Feature","properties":{"ZIP":"N3H1X4","VERTICES":6},"geometry":{"type":"Point","coordinates":[-80.36072899999999,43.391318999999996]}},{"type":"Feature","properties":{"ZIP":"N3H2K7","VERTICES":6},"geometry":{"type":"Point","coordinates":[-80.3402475,43.392318]}},{"type":"Feature","properties":{"ZIP":"N3H2R9","VERTICES":6},"geometry":{"type":"Point","coordinates":[-80.34120100000001,43.388794000000004]}},{"type":"Feature","properties":{"ZIP":"N3H2X1","VERTICES":6},"geometry":{"type":"Point","coordinates":[-80.3631885,43.3919615]}},{"type":"Feature","properties":{"ZIP":"N3H3G8","VERTICES":6},"geometry":{"type":"Point","coordinates":[-80.3412505,43.385946000000004]}},{"type":"Feature","properties":{"ZIP":"N3H3T2","VERTICES":6},"geometry":{"type":"Point","coordinates":[-80.3598355,43.397925]}},{"type":"Feature","properties":{"ZIP":"N3H3Y8","VERTICES":6},"geometry":{"type":"Point","coordinates":[-80.35449349999999,43.399702500000004]}},{"type":"Feature","properties":{"ZIP":"N3H1L1","VERTICES":6},"geometry":{"type":"Point","coordinates":[-80.362345,43.397895]}},{"type":"Feature","properties":{"ZIP":"N3H1S8","VERTICES":6},"geometry":{"type":"Point","coordinates":[-80.3583325,43.3959325]}},{"type":"Feature","properties":{"ZIP":"N3H1Z5","VERTICES":6},"geometry":{"type":"Point","coordinates":[-80.360221,43.389791]}},{"type":"Feature","properties":{"ZIP":"N3H2G1","VERTICES":6},"geometry":{"type":"Point","coordinates":[-80.3614135,43.389675]}},{"type":"Feature","properties":{"ZIP":"N3H2M8","VERTICES":6},"geometry":{"type":"Point","coordinates":[-80.352883,43.3986725]}},{"type":"Feature","properties":{"ZIP":"N3H3K1","VERTICES":6},"geometry":{"type":"Point","coordinates":[-80.3596515,43.3952115]}},{"type":"Feature","properties":{"ZIP":"N3H3P4","VERTICES":6},"geometry":{"type":"Point","coordinates":[-80.35454100000001,43.3938965]}},{"type":"Feature","properties":{"ZIP":"N3H4W6","VERTICES":6},"geometry":{"type":"Point","coordinates":[-80.32731799999999,43.389775]}},{"type":"Feature","properties":{"ZIP":"N3H5K7","VERTICES":6},"geometry":{"type":"Point","coordinates":[-80.350831,43.394063]}},{"type":"Feature","properties":{"ZIP":"N3H1V7","VERTICES":6},"geometry":{"type":"Point","coordinates":[-80.356592,43.3955975]}},{"type":"Feature","properties":{"ZIP":"N3H2P3","VERTICES":6},"geometry":{"type":"Point","coordinates":[-80.34537850000001,43.39479]}},{"type":"Feature","properties":{"ZIP":"N3H3R7","VERTICES":6},"geometry":{"type":"Point","coordinates":[-80.3444355,43.388760000000005]}},{"type":"Feature","properties":{"ZIP":"N3H4N9","VERTICES":6},"geometry":{"type":"Point","coordinates":[-80.3405475,43.39479]}},{"type":"Feature","properties":{"ZIP":"N3H5M8","VERTICES":6},"geometry":{"type":"Point","coordinates":[-80.342799,43.40438]}},{"type":"Feature","properties":{"ZIP":"N3H2L1","VERTICES":6},"geometry":{"type":"Point","coordinates":[-80.3463835,43.390615999999994]}},{"type":"Feature","properties":{"ZIP":"N3H2X2","VERTICES":6},"geometry":{"type":"Point","coordinates":[-80.3631885,43.3919615]}},{"type":"Feature","properties":{"ZIP":"N3H3B2","VERTICES":6},"geometry":{"type":"Point","coordinates":[-80.362709,43.394213]}},{"type":"Feature","properties":{"ZIP":"N3H3H4","VERTICES":6},"geometry":{"type":"Point","coordinates":[-80.33631299999999,43.3825905]}},{"type":"Feature","properties":{"ZIP":"N3H3Y9","VERTICES":6},"geometry":{"type":"Point","coordinates":[-80.3543995,43.399092]}},{"type":"Feature","properties":{"ZIP":"N3H4L5","VERTICES":6},"geometry":{"type":"Point","coordinates":[-80.3444835,43.395557]}},{"type":"Feature","properties":{"ZIP":"N3H5P8","VERTICES":6},"geometry":{"type":"Point","coordinates":[-80.3383935,43.404963499999994]}},{"type":"Feature","properties":{"ZIP":"N3H2M9","VERTICES":6},"geometry":{"type":"Point","coordinates":[-80.35299599999999,43.3986515]}},{"type":"Feature","properties":{"ZIP":"N3H2T4","VERTICES":6},"geometry":{"type":"Point","coordinates":[-80.33669950000001,43.387883]}},{"type":"Feature","properties":{"ZIP":"N3H2Y6","VERTICES":6},"geometry":{"type":"Point","coordinates":[-80.364787,43.3940035]}},{"type":"Feature","properties":{"ZIP":"N3H3K2","VERTICES":6},"geometry":{"type":"Point","coordinates":[-80.3597715,43.3952755]}},{"type":"Feature","properties":{"ZIP":"N3H4W7","VERTICES":6},"geometry":{"type":"Point","coordinates":[-80.3386735,43.3956685]}},{"type":"Feature","properties":{"ZIP":"N3H5K8","VERTICES":6},"geometry":{"type":"Point","coordinates":[-80.34854849999999,43.4021085]}},{"type":"Feature","properties":{"ZIP":"N3H1N1","VERTICES":6},"geometry":{"type":"Point","coordinates":[-80.3608315,43.397501500000004]}},{"type":"Feature","properties":{"ZIP":"N3H1V9","VERTICES":6},"geometry":{"type":"Point","coordinates":[-80.3567015,43.395484499999995]}},{"type":"Feature","properties":{"ZIP":"N3H2B3","VERTICES":6},"geometry":{"type":"Point","coordinates":[-80.34844050000001,43.398077]}},{"type":"Feature","properties":{"ZIP":"N3H2V9","VERTICES":6},"geometry":{"type":"Point","coordinates":[-80.36790500000001,43.392172]}},{"type":"Feature","properties":{"ZIP":"N3H3L5","VERTICES":6},"geometry":{"type":"Point","coordinates":[-80.35006899999999,43.3903435]}},{"type":"Feature","properties":{"ZIP":"N3H2C8","VERTICES":6},"geometry":{"type":"Point","coordinates":[-80.35520650000001,43.388780499999996]}},{"type":"Feature","properties":{"ZIP":"N3H2X3","VERTICES":6},"geometry":{"type":"Point","coordinates":[-80.361842,43.391277]}},{"type":"Feature","properties":{"ZIP":"N3H3B3","VERTICES":6},"geometry":{"type":"Point","coordinates":[-80.3631025,43.3944155]}},{"type":"Feature","properties":{"ZIP":"N3H3H6","VERTICES":6},"geometry":{"type":"Point","coordinates":[-80.33554050000001,43.381229000000005]}},{"type":"Feature","properties":{"ZIP":"N3H4E2","VERTICES":6},"geometry":{"type":"Point","coordinates":[-80.3496815,43.3995845]}},{"type":"Feature","properties":{"ZIP":"N3H5P9","VERTICES":6},"geometry":{"type":"Point","coordinates":[-80.337191,43.4052255]}},{"type":"Feature","properties":{"ZIP":"N3H1L4","VERTICES":6},"geometry":{"type":"Point","coordinates":[-80.3623945,43.397977999999995]}},{"type":"Feature","properties":{"ZIP":"N3H3C6","VERTICES":6},"geometry":{"type":"Point","coordinates":[-80.3646155,43.3964855]}},{"type":"Feature","properties":{"ZIP":"N3H3K3","VERTICES":6},"geometry":{"type":"Point","coordinates":[-80.35832300000001,43.39451]}},{"type":"Feature","properties":{"ZIP":"N3H4W8","VERTICES":6},"geometry":{"type":"Point","coordinates":[-80.33870300000001,43.395686999999995]}},{"type":"Feature","properties":{"ZIP":"N3H2P9","VERTICES":6},"geometry":{"type":"Point","coordinates":[-80.33960099999999,43.395898]}},{"type":"Feature","properties":{"ZIP":"N3H3L6","VERTICES":6},"geometry":{"type":"Point","coordinates":[-80.348434,43.389504]}},{"type":"Feature","properties":{"ZIP":"N3H3R9","VERTICES":6},"geometry":{"type":"Point","coordinates":[-80.327662,43.378667]}},{"type":"Feature","properties":{"ZIP":"N3H2X4","VERTICES":6},"geometry":{"type":"Point","coordinates":[-80.36172099999999,43.3911285]}},{"type":"Feature","properties":{"ZIP":"N3H3B4","VERTICES":6},"geometry":{"type":"Point","coordinates":[-80.361226,43.393445]}},{"type":"Feature","properties":{"ZIP":"N3H3H7","VERTICES":6},"geometry":{"type":"Point","coordinates":[-80.33712399999999,43.381934]}},{"type":"Feature","properties":{"ZIP":"N3H3T8","VERTICES":6},"geometry":{"type":"Point","coordinates":[-80.3554825,43.395680999999996]}},{"type":"Feature","properties":{"ZIP":"N3H3Z2","VERTICES":6},"geometry":{"type":"Point","coordinates":[-80.353938,43.397665]}},{"type":"Feature","properties":{"ZIP":"N3H4E3","VERTICES":6},"geometry":{"type":"Point","coordinates":[-80.349142,43.400886]}},{"type":"Feature","properties":{"ZIP":"N3H1L5","VERTICES":5},"geometry":{"type":"Point","coordinates":[-80.362404,43.3979715]}},{"type":"Feature","properties":{"ZIP":"N3H2T8","VERTICES":5},"geometry":{"type":"Point","coordinates":[-80.370159,43.40158649999999]}},{"type":"Feature","properties":{"ZIP":"N3H3C7","VERTICES":5},"geometry":{"type":"Point","coordinates":[-80.363439,43.395880000000005]}},{"type":"Feature","properties":{"ZIP":"N3H3K4","VERTICES":5},"geometry":{"type":"Point","coordinates":[-80.35855000000001,43.39463]}},{"type":"Feature","properties":{"ZIP":"N3H1W2","VERTICES":5},"geometry":{"type":"Point","coordinates":[-80.35454100000001,43.397183]}},{"type":"Feature","properties":{"ZIP":"N3H2J3","VERTICES":5},"geometry":{"type":"Point","coordinates":[-80.3494665,43.391487999999995]}},{"type":"Feature","properties":{"ZIP":"N3H3A1","VERTICES":5},"geometry":{"type":"Point","coordinates":[-80.3725625,43.398389]}},{"type":"Feature","properties":{"ZIP":"N3H5C9","VERTICES":5},"geometry":{"type":"Point","coordinates":[-80.331196,43.4008715]}},{"type":"Feature","properties":{"ZIP":"N3H1Y1","VERTICES":5},"geometry":{"type":"Point","coordinates":[-80.3544345,43.3957125]}},{"type":"Feature","properties":{"ZIP":"N3H2X5","VERTICES":5},"geometry":{"type":"Point","coordinates":[-80.3604735,43.390561500000004]}},{"type":"Feature","properties":{"ZIP":"N3H3T9","VERTICES":5},"geometry":{"type":"Point","coordinates":[-80.355509,43.395535]}},{"type":"Feature","properties":{"ZIP":"N3H3Z3","VERTICES":5},"geometry":{"type":"Point","coordinates":[-80.35372050000001,43.397009499999996]}},{"type":"Feature","properties":{"ZIP":"N3H1E5","VERTICES":5},"geometry":{"type":"Point","coordinates":[-80.363597,43.398305]}},{"type":"Feature","properties":{"ZIP":"N3H2G5","VERTICES":5},"geometry":{"type":"Point","coordinates":[-80.35919849999999,43.3878515]}},{"type":"Feature","properties":{"ZIP":"N3H5L2","VERTICES":5},"geometry":{"type":"Point","coordinates":[-80.367208,43.400062500000004]}},{"type":"Feature","properties":{"ZIP":"N3H1N5","VERTICES":5},"geometry":{"type":"Point","coordinates":[-80.3611625,43.3971645]}},{"type":"Feature","properties":{"ZIP":"N3H1W5","VERTICES":5},"geometry":{"type":"Point","coordinates":[-80.3570795,43.3950955]}},{"type":"Feature","properties":{"ZIP":"N3H3A2","VERTICES":5},"geometry":{"type":"Point","coordinates":[-80.373943,43.3985945]}},{"type":"Feature","properties":{"ZIP":"N3H4B9","VERTICES":5},"geometry":{"type":"Point","coordinates":[-80.35136349999999,43.403029000000004]}},{"type":"Feature","properties":{"ZIP":"N3H4K5","VERTICES":5},"geometry":{"type":"Point","coordinates":[-80.3488835,43.4066995]}},{"type":"Feature","properties":{"ZIP":"N3H5E4","VERTICES":5},"geometry":{"type":"Point","coordinates":[-80.34321249999999,43.398315]}},{"type":"Feature","properties":{"ZIP":"N3H1R4","VERTICES":5},"geometry":{"type":"Point","coordinates":[-80.3628545,43.3933245]}},{"type":"Feature","properties":{"ZIP":"N3H1Y4","VERTICES":5},"geometry":{"type":"Point","coordinates":[-80.35546049999999,43.3942045]}},{"type":"Feature","properties":{"ZIP":"N3H2M1","VERTICES":5},"geometry":{"type":"Point","coordinates":[-80.3398795,43.385116999999994]}},{"type":"Feature","properties":{"ZIP":"N3H3B6","VERTICES":5},"geometry":{"type":"Point","coordinates":[-80.360165,43.3928935]}},{"type":"Feature","properties":{"ZIP":"N3H3Z4","VERTICES":5},"geometry":{"type":"Point","coordinates":[-80.353354,43.3947925]}},{"type":"Feature","properties":{"ZIP":"N3H4G7","VERTICES":5},"geometry":{"type":"Point","coordinates":[-80.34769,43.3982525]}},{"type":"Feature","properties":{"ZIP":"N3H5J6","VERTICES":5},"geometry":{"type":"Point","coordinates":[-80.3776435,43.392134]}},{"type":"Feature","properties":{"ZIP":"N3H1T7","VERTICES":5},"geometry":{"type":"Point","coordinates":[-80.3621765,43.391943]}},{"type":"Feature","properties":{"ZIP":"N3H2Z1","VERTICES":5},"geometry":{"type":"Point","coordinates":[-80.3625325,43.3928605]}},{"type":"Feature","properties":{"ZIP":"N3H3W7","VERTICES":5},"geometry":{"type":"Point","coordinates":[-80.358613,43.3986275]}},{"type":"Feature","properties":{"ZIP":"N3H1N6","VERTICES":5},"geometry":{"type":"Point","coordinates":[-80.3610885,43.3972385]}},{"type":"Feature","properties":{"ZIP":"N3H3A3","VERTICES":5},"geometry":{"type":"Point","coordinates":[-80.35634300000001,43.3893315]}},{"type":"Feature","properties":{"ZIP":"N3H3M1","VERTICES":5},"geometry":{"type":"Point","coordinates":[-80.34655000000001,43.388566499999996]}},{"type":"Feature","properties":{"ZIP":"N3H3S3","VERTICES":5},"geometry":{"type":"Point","coordinates":[-80.335995,43.383601999999996]}},{"type":"Feature","properties":{"ZIP":"N3H4C1","VERTICES":5},"geometry":{"type":"Point","coordinates":[-80.351497,43.403463]}},{"type":"Feature","properties":{"ZIP":"N3H1J8","VERTICES":5},"geometry":{"type":"Point","coordinates":[-80.36678599999999,43.396994500000005]}},{"type":"Feature","properties":{"ZIP":"N3H1R6","VERTICES":5},"geometry":{"type":"Point","coordinates":[-80.363463,43.392715]}},{"type":"Feature","properties":{"ZIP":"N3H1Y6","VERTICES":5},"geometry":{"type":"Point","coordinates":[-80.356026,43.3940725]}},{"type":"Feature","properties":{"ZIP":"N3H2M2","VERTICES":5},"geometry":{"type":"Point","coordinates":[-80.33904949999999,43.3845905]}},{"type":"Feature","properties":{"ZIP":"N3H2X7","VERTICES":5},"geometry":{"type":"Point","coordinates":[-80.359053,43.3898235]}},{"type":"Feature","properties":{"ZIP":"N3H3V2","VERTICES":5},"geometry":{"type":"Point","coordinates":[-80.353449,43.394541000000004]}},{"type":"Feature","properties":{"ZIP":"N3H3Z5","VERTICES":5},"geometry":{"type":"Point","coordinates":[-80.3534285,43.3938505]}},{"type":"Feature","properties":{"ZIP":"N3H4G8","VERTICES":5},"geometry":{"type":"Point","coordinates":[-80.3470875,43.3979845]}},{"type":"Feature","properties":{"ZIP":"N3H5J7","VERTICES":5},"geometry":{"type":"Point","coordinates":[-80.378075,43.393381]}},{"type":"Feature","properties":{"ZIP":"N3H1L9","VERTICES":5},"geometry":{"type":"Point","coordinates":[-80.362741,43.397670500000004]}},{"type":"Feature","properties":{"ZIP":"N3H2A4","VERTICES":5},"geometry":{"type":"Point","coordinates":[-80.352664,43.393598499999996]}},{"type":"Feature","properties":{"ZIP":"N3H2Z2","VERTICES":5},"geometry":{"type":"Point","coordinates":[-80.36237249999999,43.392778]}},{"type":"Feature","properties":{"ZIP":"N3H4J5","VERTICES":5},"geometry":{"type":"Point","coordinates":[-80.34973550000001,43.403991500000004]}},{"type":"Feature","properties":{"ZIP":"N3H4N4","VERTICES":5},"geometry":{"type":"Point","coordinates":[-80.34101150000001,43.392819]}},{"type":"Feature","properties":{"ZIP":"N3H2B8","VERTICES":5},"geometry":{"type":"Point","coordinates":[-80.346196,43.400384]}},{"type":"Feature","properties":{"ZIP":"N3H1K1","VERTICES":5},"geometry":{"type":"Point","coordinates":[-80.36749549999999,43.395399999999995]}},{"type":"Feature","properties":{"ZIP":"N3H1R7","VERTICES":5},"geometry":{"type":"Point","coordinates":[-80.36367,43.392514000000006]}},{"type":"Feature","properties":{"ZIP":"N3H2E6","VERTICES":5},"geometry":{"type":"Point","coordinates":[-80.3643605,43.3913265]}},{"type":"Feature","properties":{"ZIP":"N3H2X8","VERTICES":5},"geometry":{"type":"Point","coordinates":[-80.3590735,43.389731]}},{"type":"Feature","properties":{"ZIP":"N3H3V3","VERTICES":5},"geometry":{"type":"Point","coordinates":[-80.3529505,43.394359]}},{"type":"Feature","properties":{"ZIP":"N3H3Z6","VERTICES":5},"geometry":{"type":"Point","coordinates":[-80.353324,43.393947499999996]}},{"type":"Feature","properties":{"ZIP":"N3H2G8","VERTICES":5},"geometry":{"type":"Point","coordinates":[-80.347583,43.397569000000004]}},{"type":"Feature","properties":{"ZIP":"N3H4A9","VERTICES":5},"geometry":{"type":"Point","coordinates":[-80.3526655,43.4009565]}},{"type":"Feature","properties":{"ZIP":"N3H4J6","VERTICES":5},"geometry":{"type":"Point","coordinates":[-80.3460615,43.397991]}},{"type":"Feature","properties":{"ZIP":"N3H0A2","VERTICES":5},"geometry":{"type":"Point","coordinates":[-80.3720845,43.3964285]}},{"type":"Feature","properties":{"ZIP":"N3H1H6","VERTICES":5},"geometry":{"type":"Point","coordinates":[-80.3798565,43.3885085]}},{"type":"Feature","properties":{"ZIP":"N3H2K2","VERTICES":5},"geometry":{"type":"Point","coordinates":[-80.3448205,43.3913445]}},{"type":"Feature","properties":{"ZIP":"N3H3G5","VERTICES":5},"geometry":{"type":"Point","coordinates":[-80.350502,43.389086]}},{"type":"Feature","properties":{"ZIP":"N3H1B3","VERTICES":5},"geometry":{"type":"Point","coordinates":[-80.3750475,43.401039499999996]}},{"type":"Feature","properties":{"ZIP":"N3H1R8","VERTICES":5},"geometry":{"type":"Point","coordinates":[-80.3640935,43.3921035]}},{"type":"Feature","properties":{"ZIP":"N3H1Z2","VERTICES":5},"geometry":{"type":"Point","coordinates":[-80.3585955,43.391453999999996]}},{"type":"Feature","properties":{"ZIP":"N3H2M5","VERTICES":5},"geometry":{"type":"Point","coordinates":[-80.338081,43.3841175]}},{"type":"Feature","properties":{"ZIP":"N3H3B9","VERTICES":5},"geometry":{"type":"Point","coordinates":[-80.358863,43.392210500000004]}},{"type":"Feature","properties":{"ZIP":"N3H3V5","VERTICES":5},"geometry":{"type":"Point","coordinates":[-80.3517675,43.393798000000004]}},{"type":"Feature","properties":{"ZIP":"N3H4V9","VERTICES":5},"geometry":{"type":"Point","coordinates":[-80.332154,43.403718]}},{"type":"Feature","properties":{"ZIP":"N3H1M2","VERTICES":5},"geometry":{"type":"Point","coordinates":[-80.36629149999999,43.394509]}},{"type":"Feature","properties":{"ZIP":"N3H1V1","VERTICES":5},"geometry":{"type":"Point","coordinates":[-80.36290299999999,43.391196]}},{"type":"Feature","properties":{"ZIP":"N3H2G9","VERTICES":5},"geometry":{"type":"Point","coordinates":[-80.3507855,43.394107500000004]}},{"type":"Feature","properties":{"ZIP":"N3H3X2","VERTICES":5},"geometry":{"type":"Point","coordinates":[-80.355069,43.396753000000004]}},{"type":"Feature","properties":{"ZIP":"N3H5B9","VERTICES":5},"geometry":{"type":"Point","coordinates":[-80.368055,43.393155]}},{"type":"Feature","properties":{"ZIP":"N3H1N9","VERTICES":5},"geometry":{"type":"Point","coordinates":[-80.36416750000001,43.394099]}},{"type":"Feature","properties":{"ZIP":"N3H2W8","VERTICES":5},"geometry":{"type":"Point","coordinates":[-80.36457300000001,43.3926565]}},{"type":"Feature","properties":{"ZIP":"N3H3G6","VERTICES":5},"geometry":{"type":"Point","coordinates":[-80.3504025,43.3892095]}},{"type":"Feature","properties":{"ZIP":"N3H3Y6","VERTICES":5},"geometry":{"type":"Point","coordinates":[-80.3550255,43.401724]}},{"type":"Feature","properties":{"ZIP":"N3H4L2","VERTICES":5},"geometry":{"type":"Point","coordinates":[-80.350804,43.403503]}},{"type":"Feature","properties":{"ZIP":"N3H3V6","VERTICES":5},"geometry":{"type":"Point","coordinates":[-80.350505,43.3931715]}},{"type":"Feature","properties":{"ZIP":"N3H4H3","VERTICES":5},"geometry":{"type":"Point","coordinates":[-80.3461245,43.398784000000006]}},{"type":"Feature","properties":{"ZIP":"N3H4W3","VERTICES":5},"geometry":{"type":"Point","coordinates":[-80.33015950000001,43.397695]}},{"type":"Feature","properties":{"ZIP":"N3H2H1","VERTICES":5},"geometry":{"type":"Point","coordinates":[-80.3517025,43.391645]}},{"type":"Feature","properties":{"ZIP":"N3H3X5","VERTICES":5},"geometry":{"type":"Point","coordinates":[-80.3600625,43.400580500000004]}},{"type":"Feature","properties":{"ZIP":"N3H4J8","VERTICES":5},"geometry":{"type":"Point","coordinates":[-80.34660400000001,43.397181]}},{"type":"Feature","properties":{"ZIP":"N3H2C5","VERTICES":5},"geometry":{"type":"Point","coordinates":[-80.356835,43.389471]}},{"type":"Feature","properties":{"ZIP":"N3H4R1","VERTICES":5},"geometry":{"type":"Point","coordinates":[-80.330961,43.389752]}},{"type":"Feature","properties":{"ZIP":"N3H1S4","VERTICES":5},"geometry":{"type":"Point","coordinates":[-80.3562245,43.39806]}},{"type":"Feature","properties":{"ZIP":"N3H1Z4","VERTICES":5},"geometry":{"type":"Point","coordinates":[-80.35940500000001,43.3906315]}},{"type":"Feature","properties":{"ZIP":"N3H2Y2","VERTICES":5},"geometry":{"type":"Point","coordinates":[-80.353789,43.39013]}},{"type":"Feature","properties":{"ZIP":"N3H3P3","VERTICES":5},"geometry":{"type":"Point","coordinates":[-80.35498849999999,43.3941125]}},{"type":"Feature","properties":{"ZIP":"N3H3V7","VERTICES":5},"geometry":{"type":"Point","coordinates":[-80.3499585,43.392793499999996]}},{"type":"Feature","properties":{"ZIP":"N3H4W5","VERTICES":5},"geometry":{"type":"Point","coordinates":[-80.3292725,43.39304799999999]}},{"type":"Feature","properties":{"ZIP":"N3H5A5","VERTICES":5},"geometry":{"type":"Point","coordinates":[-80.3269495,43.3914195]}},{"type":"Feature","properties":{"ZIP":"N3H1G3","VERTICES":5},"geometry":{"type":"Point","coordinates":[-80.34845899999999,43.403794]}},{"type":"Feature","properties":{"ZIP":"N3H1M4","VERTICES":5},"geometry":{"type":"Point","coordinates":[-80.3672525,43.3935415]}},{"type":"Feature","properties":{"ZIP":"N3H2B1","VERTICES":5},"geometry":{"type":"Point","coordinates":[-80.3491395,43.397338500000004]}},{"type":"Feature","properties":{"ZIP":"N3H2H4","VERTICES":5},"geometry":{"type":"Point","coordinates":[-80.34938650000001,43.391669]}},{"type":"Feature","properties":{"ZIP":"N3H2P2","VERTICES":5},"geometry":{"type":"Point","coordinates":[-80.3460415,43.39468]}},{"type":"Feature","properties":{"ZIP":"N3H1H9","VERTICES":5},"geometry":{"type":"Point","coordinates":[-80.37926250000001,43.390142499999996]}},{"type":"Feature","properties":{"ZIP":"N3H3B1","VERTICES":5},"geometry":{"type":"Point","coordinates":[-80.36426850000001,43.3950065]}},{"type":"Feature","properties":{"ZIP":"N3H3M9","VERTICES":5},"geometry":{"type":"Point","coordinates":[-80.3617475,43.3975995]}},{"type":"Feature","properties":{"ZIP":"N3H4C9","VERTICES":5},"geometry":{"type":"Point","coordinates":[-80.3496765,43.3986055]}},{"type":"Feature","properties":{"ZIP":"N3H4G2","VERTICES":5},"geometry":{"type":"Point","coordinates":[-80.34846,43.397348]}},{"type":"Feature","properties":{"ZIP":"N3H4L4","VERTICES":5},"geometry":{"type":"Point","coordinates":[-80.34581299999999,43.399751]}},{"type":"Feature","properties":{"ZIP":"N3H4Z3","VERTICES":5},"geometry":{"type":"Point","coordinates":[-80.3760865,43.3971925]}},{"type":"Feature","properties":{"ZIP":"N3H4A1","VERTICES":5},"geometry":{"type":"Point","coordinates":[-80.3543655,43.4031815]}},{"type":"Feature","properties":{"ZIP":"N3H1M6","VERTICES":5},"geometry":{"type":"Point","coordinates":[-80.3682305,43.392551499999996]}},{"type":"Feature","properties":{"ZIP":"N3H2H6","VERTICES":5},"geometry":{"type":"Point","coordinates":[-80.3471095,43.393975]}},{"type":"Feature","properties":{"ZIP":"N3H2V8","VERTICES":5},"geometry":{"type":"Point","coordinates":[-80.3684995,43.392474]}},{"type":"Feature","properties":{"ZIP":"N3H3L4","VERTICES":5},"geometry":{"type":"Point","coordinates":[-80.349437,43.390015000000005]}},{"type":"Feature","properties":{"ZIP":"N3H4B4","VERTICES":5},"geometry":{"type":"Point","coordinates":[-80.35258049999999,43.403204]}},{"type":"Feature","properties":{"ZIP":"N3H1A3","VERTICES":5},"geometry":{"type":"Point","coordinates":[-80.34842950000001,43.4064535]}},{"type":"Feature","properties":{"ZIP":"N3H1X5","VERTICES":5},"geometry":{"type":"Point","coordinates":[-80.36072899999999,43.391318999999996]}},{"type":"Feature","properties":{"ZIP":"N3H3N1","VERTICES":5},"geometry":{"type":"Point","coordinates":[-80.3614465,43.397445000000005]}},{"type":"Feature","properties":{"ZIP":"N3H3T6","VERTICES":5},"geometry":{"type":"Point","coordinates":[-80.35666,43.3962075]}},{"type":"Feature","properties":{"ZIP":"N3H4R3","VERTICES":5},"geometry":{"type":"Point","coordinates":[-80.3313575,43.390570499999995]}},{"type":"Feature","properties":{"ZIP":"N3H1L2","VERTICES":5},"geometry":{"type":"Point","coordinates":[-80.363002,43.3974265]}},{"type":"Feature","properties":{"ZIP":"N3H1T1","VERTICES":5},"geometry":{"type":"Point","coordinates":[-80.358487,43.395765499999996]}},{"type":"Feature","properties":{"ZIP":"N3H1Z6","VERTICES":5},"geometry":{"type":"Point","coordinates":[-80.360221,43.389791]}},{"type":"Feature","properties":{"ZIP":"N3H3V9","VERTICES":5},"geometry":{"type":"Point","coordinates":[-80.34840299999999,43.392095999999995]}},{"type":"Feature","properties":{"ZIP":"N3H4A3","VERTICES":5},"geometry":{"type":"Point","coordinates":[-80.35427050000001,43.4028855]}},{"type":"Feature","properties":{"ZIP":"N3H2H9","VERTICES":5},"geometry":{"type":"Point","coordinates":[-80.3499975,43.39094849999999]}},{"type":"Feature","properties":{"ZIP":"N3H3E7","VERTICES":5},"geometry":{"type":"Point","coordinates":[-80.3578915,43.392979499999996]}},{"type":"Feature","properties":{"ZIP":"N3H4P1","VERTICES":5},"geometry":{"type":"Point","coordinates":[-80.33990399999999,43.393084]}},{"type":"Feature","properties":{"ZIP":"N3H5M9","VERTICES":5},"geometry":{"type":"Point","coordinates":[-80.3471995,43.39138]}},{"type":"Feature","properties":{"ZIP":"N3H1P4","VERTICES":5},"geometry":{"type":"Point","coordinates":[-80.3656495,43.3926085]}},{"type":"Feature","properties":{"ZIP":"N3H1X6","VERTICES":5},"geometry":{"type":"Point","coordinates":[-80.361545,43.390491]}},{"type":"Feature","properties":{"ZIP":"N3H2L7","VERTICES":5},"geometry":{"type":"Point","coordinates":[-80.340578,43.3857255]}},{"type":"Feature","properties":{"ZIP":"N3H3T7","VERTICES":5},"geometry":{"type":"Point","coordinates":[-80.3567445,43.396336]}},{"type":"Feature","properties":{"ZIP":"N3H4G4","VERTICES":5},"geometry":{"type":"Point","coordinates":[-80.347432,43.396906]}},{"type":"Feature","properties":{"ZIP":"N3H1E2","VERTICES":5},"geometry":{"type":"Point","coordinates":[-80.36325099999999,43.398592]}},{"type":"Feature","properties":{"ZIP":"N3H1T3","VERTICES":5},"geometry":{"type":"Point","coordinates":[-80.3583785,43.395844499999995]}},{"type":"Feature","properties":{"ZIP":"N3H1Z9","VERTICES":5},"geometry":{"type":"Point","coordinates":[-80.3612655,43.387746]}},{"type":"Feature","properties":{"ZIP":"N3H3P7","VERTICES":5},"geometry":{"type":"Point","coordinates":[-80.3525635,43.3929025]}},{"type":"Feature","properties":{"ZIP":"N3H3W1","VERTICES":5},"geometry":{"type":"Point","coordinates":[-80.347972,43.391773]}},{"type":"Feature","properties":{"ZIP":"N3H1W1","VERTICES":5},"geometry":{"type":"Point","coordinates":[-80.35578799999999,43.39642]}},{"type":"Feature","properties":{"ZIP":"N3H2B4","VERTICES":5},"geometry":{"type":"Point","coordinates":[-80.3476225,43.398919500000005]}},{"type":"Feature","properties":{"ZIP":"N3H2J2","VERTICES":5},"geometry":{"type":"Point","coordinates":[-80.35081,43.3900705]}},{"type":"Feature","properties":{"ZIP":"N3H5C5","VERTICES":5},"geometry":{"type":"Point","coordinates":[-80.34961200000001,43.396846]}},{"type":"Feature","properties":{"ZIP":"N3H1J4","VERTICES":5},"geometry":{"type":"Point","coordinates":[-80.36504400000001,43.398675]}},{"type":"Feature","properties":{"ZIP":"N3H1R1","VERTICES":5},"geometry":{"type":"Point","coordinates":[-80.3611645,43.395172]}},{"type":"Feature","properties":{"ZIP":"N3H2L8","VERTICES":5},"geometry":{"type":"Point","coordinates":[-80.3440785,43.387002499999994]}},{"type":"Feature","properties":{"ZIP":"N3H1N4","VERTICES":4},"geometry":{"type":"Point","coordinates":[-80.361729,43.396687]}},{"type":"Feature","properties":{"ZIP":"N3H5N2","VERTICES":4},"geometry":{"type":"Point","coordinates":[-80.347734,43.3891255]}},{"type":"Feature","properties":{"ZIP":"N3H3B5","VERTICES":4},"geometry":{"type":"Point","coordinates":[-80.361568,43.393623]}},{"type":"Feature","properties":{"ZIP":"N3H3S2","VERTICES":4},"geometry":{"type":"Point","coordinates":[-80.338961,43.385413]}},{"type":"Feature","properties":{"ZIP":"N3H5N5","VERTICES":4},"geometry":{"type":"Point","coordinates":[-80.351992,43.3926]}},{"type":"Feature","properties":{"ZIP":"N3H1M1","VERTICES":4},"geometry":{"type":"Point","coordinates":[-80.366694,43.394093]}},{"type":"Feature","properties":{"ZIP":"N3H5B8","VERTICES":4},"geometry":{"type":"Point","coordinates":[-80.368008,43.393232999999995]}},{"type":"Feature","properties":{"ZIP":"N3H5P3","VERTICES":4},"geometry":{"type":"Point","coordinates":[-80.3764415,43.3903265]}},{"type":"Feature","properties":{"ZIP":"N3H1M3","VERTICES":4},"geometry":{"type":"Point","coordinates":[-80.3673245,43.3934705]}},{"type":"Feature","properties":{"ZIP":"N3H3M8","VERTICES":4},"geometry":{"type":"Point","coordinates":[-80.362732,43.398118999999994]}},{"type":"Feature","properties":{"ZIP":"N3H1V3","VERTICES":4},"geometry":{"type":"Point","coordinates":[-80.363684,43.39032]}},{"type":"Feature","properties":{"ZIP":"N3H1A5","VERTICES":4},"geometry":{"type":"Point","coordinates":[-80.352304,43.405611]}},{"type":"Feature","properties":{"ZIP":"N3H4J1","VERTICES":4},"geometry":{"type":"Point","coordinates":[-80.3471635,43.401395]}},{"type":"Feature","properties":{"ZIP":"N3H5K9","VERTICES":4},"geometry":{"type":"Point","coordinates":[-80.354312,43.387191]}},{"type":"Feature","properties":{"ZIP":"N3H5N1","VERTICES":4},"geometry":{"type":"Point","coordinates":[-80.376515,43.399198]}},{"type":"Feature","properties":{"ZIP":"N3H1X7","VERTICES":4},"geometry":{"type":"Point","coordinates":[-80.361545,43.390491]}},{"type":"Feature","properties":{"ZIP":"N3H3N4","VERTICES":4},"geometry":{"type":"Point","coordinates":[-80.360397,43.396915]}},{"type":"Feature","properties":{"ZIP":"N3H1J2","VERTICES":3},"geometry":{"type":"Point","coordinates":[-80.37390099999999,43.394778]}}]}