{"type":"FeatureCollection","features":[{"type":"Feature","properties":{"ZIP":"P2A2W7","VERTICES":12},"geometry":{"type":"Point","coordinates":[-80.012895,45.438131999999996]}},{"type":"Feature","properties":{"ZIP":"P2A2T6","VERTICES":10},"geometry":{"type":"Point","coordinates":[-80.028223,45.34686]}},{"type":"Feature","properties":{"ZIP":"P2A1N9","VERTICES":10},"geometry":{"type":"Point","coordinates":[-80.0218445,45.3587875]}},{"type":"Feature","properties":{"ZIP":"P2A1M6","VERTICES":10},"geometry":{"type":"Point","coordinates":[-80.0289195,45.3555425]}},{"type":"Feature","properties":{"ZIP":"P2A0A2","VERTICES":10},"geometry":{"type":"Point","coordinates":[-80.04502,45.3476875]}},{"type":"Feature","properties":{"ZIP":"P2A2R2","VERTICES":10},"geometry":{"type":"Point","coordinates":[-80.0239725,45.3390455]}},{"type":"Feature","properties":{"ZIP":"P2A2J3","VERTICES":9},"geometry":{"type":"Point","coordinates":[-80.024617,45.357806]}},{"type":"Feature","properties":{"ZIP":"P2A2R6","VERTICES":9},"geometry":{"type":"Point","coordinates":[-80.0201745,45.337039000000004]}},{"type":"Feature","properties":{"ZIP":"P2A1C2","VERTICES":9},"geometry":{"type":"Point","coordinates":[-80.0408985,45.346826]}},{"type":"Feature","properties":{"ZIP":"P2A1J8","VERTICES":9},"geometry":{"type":"Point","coordinates":[-80.03104049999999,45.352146]}},{"type":"Feature","properties":{"ZIP":"P2A2H5","VERTICES":9},"geometry":{"type":"Point","coordinates":[-80.030236,45.356431]}},{"type":"Feature","properties":{"ZIP":"P2A2W8","VERTICES":9},"geometry":{"type":"Point","coordinates":[-79.9180575,45.301120499999996]}},{"type":"Feature","properties":{"ZIP":"P2A2Y9","VERTICES":9},"geometry":{"type":"Point","coordinates":[-80.01952,45.3463205]}},{"type":"Feature","properties":{"ZIP":"P2A1S9","VERTICES":9},"geometry":{"type":"Point","coordinates":[-80.0325945,45.346810500000004]}},{"type":"Feature","properties":{"ZIP":"P2A2C6","VERTICES":9},"geometry":{"type":"Point","coordinates":[-80.0427615,45.349757499999996]}},{"type":"Feature","properties":{"ZIP":"P2A1P9","VERTICES":9},"geometry":{"type":"Point","coordinates":[-80.02541500000001,45.360235]}},{"type":"Feature","properties":{"ZIP":"P2A2P6","VERTICES":9},"geometry":{"type":"Point","coordinates":[-80.02891600000001,45.332004]}},{"type":"Feature","properties":{"ZIP":"P2A2M4","VERTICES":9},"geometry":{"type":"Point","coordinates":[-80.03674,45.361099499999995]}},{"type":"Feature","properties":{"ZIP":"P2A2M5","VERTICES":9},"geometry":{"type":"Point","coordinates":[-80.0247545,45.3372525]}},{"type":"Feature","properties":{"ZIP":"P2A2N2","VERTICES":9},"geometry":{"type":"Point","coordinates":[-80.026229,45.335486]}},{"type":"Feature","properties":{"ZIP":"P2A1Y8","VERTICES":9},"geometry":{"type":"Point","coordinates":[-80.03616550000001,45.351278]}},{"type":"Feature","properties":{"ZIP":"P2A1X7","VERTICES":8},"geometry":{"type":"Point","coordinates":[-80.0347935,45.353365999999994]}},{"type":"Feature","properties":{"ZIP":"P2A1T7","VERTICES":8},"geometry":{"type":"Point","coordinates":[-80.03515250000001,45.345803000000004]}},{"type":"Feature","properties":{"ZIP":"P2A1X8","VERTICES":8},"geometry":{"type":"Point","coordinates":[-80.03478849999999,45.353449499999996]}},{"type":"Feature","properties":{"ZIP":"P2A2T7","VERTICES":8},"geometry":{"type":"Point","coordinates":[-80.02962500000001,45.345053]}},{"type":"Feature","properties":{"ZIP":"P2A1J3","VERTICES":8},"geometry":{"type":"Point","coordinates":[-80.0376045,45.3519395]}},{"type":"Feature","properties":{"ZIP":"P2A1C1","VERTICES":8},"geometry":{"type":"Point","coordinates":[-80.0391655,45.345501]}},{"type":"Feature","properties":{"ZIP":"P2A1L4","VERTICES":8},"geometry":{"type":"Point","coordinates":[-80.02643,45.354233]}},{"type":"Feature","properties":{"ZIP":"P2A1S5","VERTICES":8},"geometry":{"type":"Point","coordinates":[-80.0351125,45.3404785]}},{"type":"Feature","properties":{"ZIP":"P2A2R7","VERTICES":8},"geometry":{"type":"Point","coordinates":[-80.0202385,45.336504]}},{"type":"Feature","properties":{"ZIP":"P2A1M7","VERTICES":8},"geometry":{"type":"Point","coordinates":[-80.02914899999999,45.3554515]}},{"type":"Feature","properties":{"ZIP":"P2A1J6","VERTICES":8},"geometry":{"type":"Point","coordinates":[-80.0303375,45.3519955]}},{"type":"Feature","properties":{"ZIP":"P2A1P2","VERTICES":8},"geometry":{"type":"Point","coordinates":[-80.022958,45.359493]}},{"type":"Feature","properties":{"ZIP":"P2A1L5","VERTICES":8},"geometry":{"type":"Point","coordinates":[-80.0273195,45.3548715]}},{"type":"Feature","properties":{"ZIP":"P2A1S7","VERTICES":8},"geometry":{"type":"Point","coordinates":[-80.032669,45.3445385]}},{"type":"Feature","properties":{"ZIP":"P2A1V2","VERTICES":8},"geometry":{"type":"Point","coordinates":[-80.0304195,45.349858999999995]}},{"type":"Feature","properties":{"ZIP":"P2A3A8","VERTICES":8},"geometry":{"type":"Point","coordinates":[-80.0271745,45.3533605]}},{"type":"Feature","properties":{"ZIP":"P2A1W9","VERTICES":8},"geometry":{"type":"Point","coordinates":[-80.035201,45.344719]}},{"type":"Feature","properties":{"ZIP":"P2A2P4","VERTICES":8},"geometry":{"type":"Point","coordinates":[-80.0285615,45.334574]}},{"type":"Feature","properties":{"ZIP":"P2A2P5","VERTICES":8},"geometry":{"type":"Point","coordinates":[-80.028816,45.33274]}},{"type":"Feature","properties":{"ZIP":"P2A2W9","VERTICES":8},"geometry":{"type":"Point","coordinates":[-80.0461425,45.389433]}},{"type":"Feature","properties":{"ZIP":"P2A2M1","VERTICES":8},"geometry":{"type":"Point","coordinates":[-80.0300315,45.3411245]}},{"type":"Feature","properties":{"ZIP":"P2A3B2","VERTICES":8},"geometry":{"type":"Point","coordinates":[-80.0427525,45.345795]}},{"type":"Feature","properties":{"ZIP":"P2A1L8","VERTICES":8},"geometry":{"type":"Point","coordinates":[-80.02376749999999,45.357029999999995]}},{"type":"Feature","properties":{"ZIP":"P2A2Z2","VERTICES":8},"geometry":{"type":"Point","coordinates":[-80.027989,45.360057999999995]}},{"type":"Feature","properties":{"ZIP":"P2A1N3","VERTICES":8},"geometry":{"type":"Point","coordinates":[-80.040149,45.352972]}},{"type":"Feature","properties":{"ZIP":"P2A2V5","VERTICES":8},"geometry":{"type":"Point","coordinates":[-80.0243645,45.345333]}},{"type":"Feature","properties":{"ZIP":"P2A1X3","VERTICES":8},"geometry":{"type":"Point","coordinates":[-80.035141,45.3472125]}},{"type":"Feature","properties":{"ZIP":"P2A2P9","VERTICES":8},"geometry":{"type":"Point","coordinates":[-80.02319,45.3403155]}},{"type":"Feature","properties":{"ZIP":"P2A2S7","VERTICES":8},"geometry":{"type":"Point","coordinates":[-80.0173495,45.344366]}},{"type":"Feature","properties":{"ZIP":"P2A1K4","VERTICES":8},"geometry":{"type":"Point","coordinates":[-80.0361045,45.3525015]}},{"type":"Feature","properties":{"ZIP":"P2A1X4","VERTICES":8},"geometry":{"type":"Point","coordinates":[-80.03500650000001,45.3491715]}},{"type":"Feature","properties":{"ZIP":"P2A2K8","VERTICES":8},"geometry":{"type":"Point","coordinates":[-80.0272585,45.343985]}},{"type":"Feature","properties":{"ZIP":"P2A2M6","VERTICES":8},"geometry":{"type":"Point","coordinates":[-80.026495,45.362221500000004]}},{"type":"Feature","properties":{"ZIP":"P2A1X5","VERTICES":8},"geometry":{"type":"Point","coordinates":[-80.0350485,45.3503575]}},{"type":"Feature","properties":{"ZIP":"P2A1N7","VERTICES":8},"geometry":{"type":"Point","coordinates":[-80.023383,45.35793]}},{"type":"Feature","properties":{"ZIP":"P2A1X6","VERTICES":8},"geometry":{"type":"Point","coordinates":[-80.034904,45.351239]}},{"type":"Feature","properties":{"ZIP":"P2A2R4","VERTICES":8},"geometry":{"type":"Point","coordinates":[-80.02181200000001,45.337127499999994]}},{"type":"Feature","properties":{"ZIP":"P2A2Z7","VERTICES":8},"geometry":{"type":"Point","coordinates":[-80.027624,45.3599255]}},{"type":"Feature","properties":{"ZIP":"P2A1K7","VERTICES":7},"geometry":{"type":"Point","coordinates":[-80.026404,45.3518015]}},{"type":"Feature","properties":{"ZIP":"P2A2L4","VERTICES":7},"geometry":{"type":"Point","coordinates":[-80.0231665,45.343446]}},{"type":"Feature","properties":{"ZIP":"P2A2W4","VERTICES":7},"geometry":{"type":"Point","coordinates":[-80.0195145,45.34538]}},{"type":"Feature","properties":{"ZIP":"P2A1B9","VERTICES":7},"geometry":{"type":"Point","coordinates":[-80.0397775,45.345648999999995]}},{"type":"Feature","properties":{"ZIP":"P2A1S4","VERTICES":7},"geometry":{"type":"Point","coordinates":[-80.03663449999999,45.339411999999996]}},{"type":"Feature","properties":{"ZIP":"P2A2C2","VERTICES":7},"geometry":{"type":"Point","coordinates":[-80.04114,45.349613500000004]}},{"type":"Feature","properties":{"ZIP":"P2A1P1","VERTICES":7},"geometry":{"type":"Point","coordinates":[-80.021907,45.358665]}},{"type":"Feature","properties":{"ZIP":"P2A2A6","VERTICES":7},"geometry":{"type":"Point","coordinates":[-80.038254,45.3449375]}},{"type":"Feature","properties":{"ZIP":"P2A2N8","VERTICES":7},"geometry":{"type":"Point","coordinates":[-80.03010950000001,45.3377365]}},{"type":"Feature","properties":{"ZIP":"P2A2T8","VERTICES":7},"geometry":{"type":"Point","coordinates":[-80.027391,45.3478505]}},{"type":"Feature","properties":{"ZIP":"P2A3A7","VERTICES":7},"geometry":{"type":"Point","coordinates":[-80.026735,45.3530285]}},{"type":"Feature","properties":{"ZIP":"P2A2Y8","VERTICES":7},"geometry":{"type":"Point","coordinates":[-80.021916,45.3538675]}},{"type":"Feature","properties":{"ZIP":"P2A1H2","VERTICES":7},"geometry":{"type":"Point","coordinates":[-80.03833499999999,45.3499695]}},{"type":"Feature","properties":{"ZIP":"P2A2V1","VERTICES":7},"geometry":{"type":"Point","coordinates":[-80.02818049999999,45.345136]}},{"type":"Feature","properties":{"ZIP":"P2A1A5","VERTICES":7},"geometry":{"type":"Point","coordinates":[-80.0381545,45.341991]}},{"type":"Feature","properties":{"ZIP":"P2A2A9","VERTICES":7},"geometry":{"type":"Point","coordinates":[-80.039633,45.349897]}},{"type":"Feature","properties":{"ZIP":"P2A1C3","VERTICES":7},"geometry":{"type":"Point","coordinates":[-80.0421105,45.3479375]}},{"type":"Feature","properties":{"ZIP":"P2A1Y2","VERTICES":7},"geometry":{"type":"Point","coordinates":[-80.034883,45.3463165]}},{"type":"Feature","properties":{"ZIP":"P2A2C5","VERTICES":7},"geometry":{"type":"Point","coordinates":[-80.042735,45.350175]}},{"type":"Feature","properties":{"ZIP":"P2A1N1","VERTICES":7},"geometry":{"type":"Point","coordinates":[-80.0365635,45.353936000000004]}},{"type":"Feature","properties":{"ZIP":"P2A1Z6","VERTICES":7},"geometry":{"type":"Point","coordinates":[-80.03671,45.356742999999994]}},{"type":"Feature","properties":{"ZIP":"P2A2L9","VERTICES":7},"geometry":{"type":"Point","coordinates":[-80.024635,45.3417265]}},{"type":"Feature","properties":{"ZIP":"P2A2V2","VERTICES":7},"geometry":{"type":"Point","coordinates":[-80.02830449999999,45.344958000000005]}},{"type":"Feature","properties":{"ZIP":"P2A1P8","VERTICES":7},"geometry":{"type":"Point","coordinates":[-80.0255355,45.3602635]}},{"type":"Feature","properties":{"ZIP":"P2A2B1","VERTICES":7},"geometry":{"type":"Point","coordinates":[-80.0396505,45.350162999999995]}},{"type":"Feature","properties":{"ZIP":"P2A1V4","VERTICES":7},"geometry":{"type":"Point","coordinates":[-80.0271205,45.352006]}},{"type":"Feature","properties":{"ZIP":"P2A1Z7","VERTICES":7},"geometry":{"type":"Point","coordinates":[-80.03652249999999,45.3563945]}},{"type":"Feature","properties":{"ZIP":"P2A2H7","VERTICES":7},"geometry":{"type":"Point","coordinates":[-80.0301785,45.3566125]}},{"type":"Feature","properties":{"ZIP":"P2A2S6","VERTICES":7},"geometry":{"type":"Point","coordinates":[-80.0171675,45.344361000000006]}},{"type":"Feature","properties":{"ZIP":"P2A2H8","VERTICES":7},"geometry":{"type":"Point","coordinates":[-80.0258035,45.3581055]}},{"type":"Feature","properties":{"ZIP":"P2A2K7","VERTICES":7},"geometry":{"type":"Point","coordinates":[-80.0276195,45.3435425]}},{"type":"Feature","properties":{"ZIP":"P2A1Z9","VERTICES":7},"geometry":{"type":"Point","coordinates":[-80.036349,45.341207499999996]}},{"type":"Feature","properties":{"ZIP":"P2A2R1","VERTICES":7},"geometry":{"type":"Point","coordinates":[-80.022718,45.3426575]}},{"type":"Feature","properties":{"ZIP":"P2A1M1","VERTICES":7},"geometry":{"type":"Point","coordinates":[-80.023136,45.357547]}},{"type":"Feature","properties":{"ZIP":"P2A1Y6","VERTICES":7},"geometry":{"type":"Point","coordinates":[-80.0363275,45.347235999999995]}},{"type":"Feature","properties":{"ZIP":"P2A2C9","VERTICES":7},"geometry":{"type":"Point","coordinates":[-80.04403400000001,45.3497005]}},{"type":"Feature","properties":{"ZIP":"P2A2A1","VERTICES":7},"geometry":{"type":"Point","coordinates":[-80.0372,45.342465000000004]}},{"type":"Feature","properties":{"ZIP":"P2A1T5","VERTICES":7},"geometry":{"type":"Point","coordinates":[-80.03416849999999,45.344137]}},{"type":"Feature","properties":{"ZIP":"P2A2E1","VERTICES":7},"geometry":{"type":"Point","coordinates":[-80.04441550000001,45.3500425]}},{"type":"Feature","properties":{"ZIP":"P2A2W1","VERTICES":7},"geometry":{"type":"Point","coordinates":[-80.021831,45.3454375]}},{"type":"Feature","properties":{"ZIP":"P2A2H1","VERTICES":7},"geometry":{"type":"Point","coordinates":[-80.033195,45.353402]}},{"type":"Feature","properties":{"ZIP":"P2A3C4","VERTICES":7},"geometry":{"type":"Point","coordinates":[-80.04002600000001,45.3579215]}},{"type":"Feature","properties":{"ZIP":"P2A1S3","VERTICES":6},"geometry":{"type":"Point","coordinates":[-80.037445,45.339169]}},{"type":"Feature","properties":{"ZIP":"P2A2C1","VERTICES":6},"geometry":{"type":"Point","coordinates":[-80.04124250000001,45.349336]}},{"type":"Feature","properties":{"ZIP":"P2A2R5","VERTICES":6},"geometry":{"type":"Point","coordinates":[-80.02165500000001,45.3363435]}},{"type":"Feature","properties":{"ZIP":"P2A1M5","VERTICES":6},"geometry":{"type":"Point","coordinates":[-80.0278025,45.3555635]}},{"type":"Feature","properties":{"ZIP":"P2A2E3","VERTICES":6},"geometry":{"type":"Point","coordinates":[-80.041685,45.353662]}},{"type":"Feature","properties":{"ZIP":"P2A1J1","VERTICES":6},"geometry":{"type":"Point","coordinates":[-80.043792,45.351093500000005]}},{"type":"Feature","properties":{"ZIP":"P2A1W5","VERTICES":6},"geometry":{"type":"Point","coordinates":[-80.03545199999999,45.341819]}},{"type":"Feature","properties":{"ZIP":"P2A2A5","VERTICES":6},"geometry":{"type":"Point","coordinates":[-80.037175,45.342303]}},{"type":"Feature","properties":{"ZIP":"P2A1T9","VERTICES":6},"geometry":{"type":"Point","coordinates":[-80.0340105,45.3469795]}},{"type":"Feature","properties":{"ZIP":"P2A1Z2","VERTICES":6},"geometry":{"type":"Point","coordinates":[-80.03611000000001,45.3532195]}},{"type":"Feature","properties":{"ZIP":"P2A3A4","VERTICES":6},"geometry":{"type":"Point","coordinates":[-80.0202025,45.3410545]}},{"type":"Feature","properties":{"ZIP":"P2A2H3","VERTICES":6},"geometry":{"type":"Point","coordinates":[-80.0293255,45.3532485]}},{"type":"Feature","properties":{"ZIP":"P2A1G7","VERTICES":6},"geometry":{"type":"Point","coordinates":[-80.0392255,45.348442]}},{"type":"Feature","properties":{"ZIP":"P2A1V1","VERTICES":6},"geometry":{"type":"Point","coordinates":[-80.031092,45.3495415]}},{"type":"Feature","properties":{"ZIP":"P2A1Z3","VERTICES":6},"geometry":{"type":"Point","coordinates":[-80.03610549999999,45.353468]}},{"type":"Feature","properties":{"ZIP":"P2A2L7","VERTICES":6},"geometry":{"type":"Point","coordinates":[-80.01481100000001,45.3438295]}},{"type":"Feature","properties":{"ZIP":"P2A1W8","VERTICES":6},"geometry":{"type":"Point","coordinates":[-80.035472,45.3426755]}},{"type":"Feature","properties":{"ZIP":"P2A2P3","VERTICES":6},"geometry":{"type":"Point","coordinates":[-80.02846249999999,45.3353105]}},{"type":"Feature","properties":{"ZIP":"P2A1Y1","VERTICES":6},"geometry":{"type":"Point","coordinates":[-80.0347825,45.354953]}},{"type":"Feature","properties":{"ZIP":"P2A2C4","VERTICES":6},"geometry":{"type":"Point","coordinates":[-80.0410565,45.351789]}},{"type":"Feature","properties":{"ZIP":"P2A2K1","VERTICES":6},"geometry":{"type":"Point","coordinates":[-80.0248295,45.352669000000006]}},{"type":"Feature","properties":{"ZIP":"P2A1M8","VERTICES":6},"geometry":{"type":"Point","coordinates":[-80.03178,45.3551365]}},{"type":"Feature","properties":{"ZIP":"P2A1Z4","VERTICES":6},"geometry":{"type":"Point","coordinates":[-80.036119,45.354780000000005]}},{"type":"Feature","properties":{"ZIP":"P2A2E7","VERTICES":6},"geometry":{"type":"Point","coordinates":[-80.04048850000001,45.3541585]}},{"type":"Feature","properties":{"ZIP":"P2A2L8","VERTICES":6},"geometry":{"type":"Point","coordinates":[-80.0172795,45.342514]}},{"type":"Feature","properties":{"ZIP":"P2A1L6","VERTICES":6},"geometry":{"type":"Point","coordinates":[-80.0316035,45.3534305]}},{"type":"Feature","properties":{"ZIP":"P2A2S4","VERTICES":6},"geometry":{"type":"Point","coordinates":[-80.0256915,45.345258]}},{"type":"Feature","properties":{"ZIP":"P2A1V3","VERTICES":6},"geometry":{"type":"Point","coordinates":[-80.0273635,45.3518995]}},{"type":"Feature","properties":{"ZIP":"P2A1A7","VERTICES":6},"geometry":{"type":"Point","coordinates":[-80.0380605,45.34294250000001]}},{"type":"Feature","properties":{"ZIP":"P2A1J9","VERTICES":6},"geometry":{"type":"Point","coordinates":[-80.030745,45.3521365]}},{"type":"Feature","properties":{"ZIP":"P2A1Y3","VERTICES":6},"geometry":{"type":"Point","coordinates":[-80.0366465,45.344277]}},{"type":"Feature","properties":{"ZIP":"P2A2K3","VERTICES":6},"geometry":{"type":"Point","coordinates":[-80.02303699999999,45.3537135]}},{"type":"Feature","properties":{"ZIP":"P2A1H4","VERTICES":6},"geometry":{"type":"Point","coordinates":[-80.034269,45.349588]}},{"type":"Feature","properties":{"ZIP":"P2A1N2","VERTICES":6},"geometry":{"type":"Point","coordinates":[-80.0346835,45.3544]}},{"type":"Feature","properties":{"ZIP":"P2A2G3","VERTICES":6},"geometry":{"type":"Point","coordinates":[-80.039053,45.357309]}},{"type":"Feature","properties":{"ZIP":"P2A1X2","VERTICES":6},"geometry":{"type":"Point","coordinates":[-80.035112,45.3475315]}},{"type":"Feature","properties":{"ZIP":"P2A1T1","VERTICES":6},"geometry":{"type":"Point","coordinates":[-80.032592,45.346810500000004]}},{"type":"Feature","properties":{"ZIP":"P2A1Y4","VERTICES":6},"geometry":{"type":"Point","coordinates":[-80.036377,45.3460755]}},{"type":"Feature","properties":{"ZIP":"P2A2C7","VERTICES":6},"geometry":{"type":"Point","coordinates":[-80.0426065,45.351785]}},{"type":"Feature","properties":{"ZIP":"P2A1H5","VERTICES":6},"geometry":{"type":"Point","coordinates":[-80.040449,45.351053]}},{"type":"Feature","properties":{"ZIP":"P2A1Z8","VERTICES":6},"geometry":{"type":"Point","coordinates":[-80.03621749999999,45.3412215]}},{"type":"Feature","properties":{"ZIP":"P2A2G5","VERTICES":6},"geometry":{"type":"Point","coordinates":[-80.04049549999999,45.3596275]}},{"type":"Feature","properties":{"ZIP":"P2A1R2","VERTICES":6},"geometry":{"type":"Point","coordinates":[-80.031099,45.356808]}},{"type":"Feature","properties":{"ZIP":"P2A2B5","VERTICES":6},"geometry":{"type":"Point","coordinates":[-80.0418885,45.3460925]}},{"type":"Feature","properties":{"ZIP":"P2A1L9","VERTICES":6},"geometry":{"type":"Point","coordinates":[-80.0212935,45.357878]}},{"type":"Feature","properties":{"ZIP":"P2A1T2","VERTICES":6},"geometry":{"type":"Point","coordinates":[-80.034316,45.342637499999995]}},{"type":"Feature","properties":{"ZIP":"P2A1Y5","VERTICES":6},"geometry":{"type":"Point","coordinates":[-80.03631949999999,45.3474005]}},{"type":"Feature","properties":{"ZIP":"P2A2C8","VERTICES":6},"geometry":{"type":"Point","coordinates":[-80.0426105,45.3516875]}},{"type":"Feature","properties":{"ZIP":"P2A2Z3","VERTICES":6},"geometry":{"type":"Point","coordinates":[-80.01962850000001,45.347156999999996]}},{"type":"Feature","properties":{"ZIP":"P2A1N5","VERTICES":6},"geometry":{"type":"Point","coordinates":[-80.0283635,45.354960000000005]}},{"type":"Feature","properties":{"ZIP":"P2A1V6","VERTICES":6},"geometry":{"type":"Point","coordinates":[-80.02345700000001,45.354278]}},{"type":"Feature","properties":{"ZIP":"P2A1B2","VERTICES":6},"geometry":{"type":"Point","coordinates":[-80.0329635,45.343525]}},{"type":"Feature","properties":{"ZIP":"P2A2B6","VERTICES":6},"geometry":{"type":"Point","coordinates":[-80.04231,45.3469615]}},{"type":"Feature","properties":{"ZIP":"P2A2H9","VERTICES":6},"geometry":{"type":"Point","coordinates":[-80.026114,45.358385999999996]}},{"type":"Feature","properties":{"ZIP":"P2A1T4","VERTICES":6},"geometry":{"type":"Point","coordinates":[-80.0342465,45.342760999999996]}},{"type":"Feature","properties":{"ZIP":"P2A1H7","VERTICES":6},"geometry":{"type":"Point","coordinates":[-80.04182850000001,45.351093]}},{"type":"Feature","properties":{"ZIP":"P2A1N6","VERTICES":6},"geometry":{"type":"Point","coordinates":[-80.02836400000001,45.3549595]}},{"type":"Feature","properties":{"ZIP":"P2A2G8","VERTICES":6},"geometry":{"type":"Point","coordinates":[-80.03324599999999,45.353384000000005]}},{"type":"Feature","properties":{"ZIP":"P2A1K5","VERTICES":6},"geometry":{"type":"Point","coordinates":[-80.0392095,45.3525865]}},{"type":"Feature","properties":{"ZIP":"P2A2J1","VERTICES":6},"geometry":{"type":"Point","coordinates":[-80.026561,45.3592975]}},{"type":"Feature","properties":{"ZIP":"P2A2X4","VERTICES":6},"geometry":{"type":"Point","coordinates":[-80.0368975,45.345479499999996]}},{"type":"Feature","properties":{"ZIP":"P2A1Y7","VERTICES":6},"geometry":{"type":"Point","coordinates":[-80.036236,45.3493945]}},{"type":"Feature","properties":{"ZIP":"P2A2L2","VERTICES":6},"geometry":{"type":"Point","coordinates":[-80.0216865,45.3433245]}},{"type":"Feature","properties":{"ZIP":"P2A2Z6","VERTICES":6},"geometry":{"type":"Point","coordinates":[-80.044202,45.3531225]}},{"type":"Feature","properties":{"ZIP":"P2A1H8","VERTICES":6},"geometry":{"type":"Point","coordinates":[-80.04182850000001,45.351093]}},{"type":"Feature","properties":{"ZIP":"P2A2A2","VERTICES":6},"geometry":{"type":"Point","coordinates":[-80.03875149999999,45.342385]}},{"type":"Feature","properties":{"ZIP":"P2A3C1","VERTICES":6},"geometry":{"type":"Point","coordinates":[-80.02128300000001,45.349579]}},{"type":"Feature","properties":{"ZIP":"P2A1M4","VERTICES":6},"geometry":{"type":"Point","coordinates":[-80.0272095,45.3557345]}},{"type":"Feature","properties":{"ZIP":"P2A1T6","VERTICES":6},"geometry":{"type":"Point","coordinates":[-80.03109549999999,45.3410595]}},{"type":"Feature","properties":{"ZIP":"P2A2E2","VERTICES":6},"geometry":{"type":"Point","coordinates":[-80.041691,45.3533415]}},{"type":"Feature","properties":{"ZIP":"P2A2T2","VERTICES":6},"geometry":{"type":"Point","coordinates":[-80.021132,45.347106]}},{"type":"Feature","properties":{"ZIP":"P2A0B5","VERTICES":6},"geometry":{"type":"Point","coordinates":[-79.8960525,45.4470435]}},{"type":"Feature","properties":{"ZIP":"P2A1H9","VERTICES":6},"geometry":{"type":"Point","coordinates":[-80.0433525,45.3511735]}},{"type":"Feature","properties":{"ZIP":"P2A1N8","VERTICES":6},"geometry":{"type":"Point","coordinates":[-80.021458,45.359015]}},{"type":"Feature","properties":{"ZIP":"P2A2A4","VERTICES":6},"geometry":{"type":"Point","coordinates":[-80.03739350000001,45.342291]}},{"type":"Feature","properties":{"ZIP":"P2A2N3","VERTICES":6},"geometry":{"type":"Point","coordinates":[-80.0269595,45.3348405]}},{"type":"Feature","properties":{"ZIP":"P2A1B8","VERTICES":5},"geometry":{"type":"Point","coordinates":[-80.0387035,45.344538]}},{"type":"Feature","properties":{"ZIP":"P2A1G0","VERTICES":5},"geometry":{"type":"Point","coordinates":[-80.18635800000001,45.409527]}},{"type":"Feature","properties":{"ZIP":"P2A1Z1","VERTICES":5},"geometry":{"type":"Point","coordinates":[-80.03628,45.348079]}},{"type":"Feature","properties":{"ZIP":"P2A3A1","VERTICES":5},"geometry":{"type":"Point","coordinates":[-80.019936,45.3461045]}},{"type":"Feature","properties":{"ZIP":"P2A2N7","VERTICES":5},"geometry":{"type":"Point","coordinates":[-80.03082699999999,45.3422235]}},{"type":"Feature","properties":{"ZIP":"P2A2J4","VERTICES":5},"geometry":{"type":"Point","coordinates":[-80.024524,45.3579625]}},{"type":"Feature","properties":{"ZIP":"P2A2Y5","VERTICES":5},"geometry":{"type":"Point","coordinates":[-80.0196415,45.3461255]}},{"type":"Feature","properties":{"ZIP":"P2A2E5","VERTICES":5},"geometry":{"type":"Point","coordinates":[-80.04016999999999,45.353086000000005]}},{"type":"Feature","properties":{"ZIP":"P2A2L5","VERTICES":5},"geometry":{"type":"Point","coordinates":[-80.022008,45.3432155]}},{"type":"Feature","properties":{"ZIP":"P2A1A2","VERTICES":5},"geometry":{"type":"Point","coordinates":[-80.0369035,45.340326000000005]}},{"type":"Feature","properties":{"ZIP":"P2A1W7","VERTICES":5},"geometry":{"type":"Point","coordinates":[-80.035419,45.3416895]}},{"type":"Feature","properties":{"ZIP":"P2A1X9","VERTICES":5},"geometry":{"type":"Point","coordinates":[-80.0347745,45.354929]}},{"type":"Feature","properties":{"ZIP":"P2A2C3","VERTICES":5},"geometry":{"type":"Point","coordinates":[-80.0410465,45.3515635]}},{"type":"Feature","properties":{"ZIP":"P2A2J9","VERTICES":5},"geometry":{"type":"Point","coordinates":[-80.02473499999999,45.3527225]}},{"type":"Feature","properties":{"ZIP":"P2A2Y6","VERTICES":5},"geometry":{"type":"Point","coordinates":[-80.0389955,45.344832999999994]}},{"type":"Feature","properties":{"ZIP":"P2A2E6","VERTICES":5},"geometry":{"type":"Point","coordinates":[-80.04052200000001,45.354215499999995]}},{"type":"Feature","properties":{"ZIP":"P2A2A7","VERTICES":5},"geometry":{"type":"Point","coordinates":[-80.0382095,45.345313]}},{"type":"Feature","properties":{"ZIP":"P2A2H4","VERTICES":5},"geometry":{"type":"Point","coordinates":[-80.02934350000001,45.353256]}},{"type":"Feature","properties":{"ZIP":"P2A2S3","VERTICES":5},"geometry":{"type":"Point","coordinates":[-80.02540250000001,45.3451455]}},{"type":"Feature","properties":{"ZIP":"P2A1P3","VERTICES":5},"geometry":{"type":"Point","coordinates":[-80.022025,45.357678]}},{"type":"Feature","properties":{"ZIP":"P2A1S8","VERTICES":5},"geometry":{"type":"Point","coordinates":[-80.03264999999999,45.344892]}},{"type":"Feature","properties":{"ZIP":"P2A2K2","VERTICES":5},"geometry":{"type":"Point","coordinates":[-80.023341,45.353551499999995]}},{"type":"Feature","properties":{"ZIP":"P2A1H3","VERTICES":5},"geometry":{"type":"Point","coordinates":[-80.03466599999999,45.3495915]}},{"type":"Feature","properties":{"ZIP":"P2A2E8","VERTICES":5},"geometry":{"type":"Point","coordinates":[-80.0383175,45.351592]}},{"type":"Feature","properties":{"ZIP":"P2A1X1","VERTICES":5},"geometry":{"type":"Point","coordinates":[-80.035754,45.3418175]}},{"type":"Feature","properties":{"ZIP":"P2A2H6","VERTICES":5},"geometry":{"type":"Point","coordinates":[-80.03025099999999,45.356336999999996]}},{"type":"Feature","properties":{"ZIP":"P2A1C4","VERTICES":5},"geometry":{"type":"Point","coordinates":[-80.042387,45.3481785]}},{"type":"Feature","properties":{"ZIP":"P2A1L7","VERTICES":5},"geometry":{"type":"Point","coordinates":[-80.031965,45.3532255]}},{"type":"Feature","properties":{"ZIP":"P2A2S5","VERTICES":5},"geometry":{"type":"Point","coordinates":[-80.0160025,45.3444185]}},{"type":"Feature","properties":{"ZIP":"P2A2V3","VERTICES":5},"geometry":{"type":"Point","coordinates":[-80.0247155,45.344904]}},{"type":"Feature","properties":{"ZIP":"P2A1A9","VERTICES":5},"geometry":{"type":"Point","coordinates":[-80.03136,45.3436215]}},{"type":"Feature","properties":{"ZIP":"P2A1K1","VERTICES":5},"geometry":{"type":"Point","coordinates":[-80.0354875,45.3523725]}},{"type":"Feature","properties":{"ZIP":"P2A2B4","VERTICES":5},"geometry":{"type":"Point","coordinates":[-80.039978,45.3445215]}},{"type":"Feature","properties":{"ZIP":"P2A1C5","VERTICES":5},"geometry":{"type":"Point","coordinates":[-80.043572,45.3485635]}},{"type":"Feature","properties":{"ZIP":"P2A2K4","VERTICES":5},"geometry":{"type":"Point","coordinates":[-80.02202600000001,45.3544175]}},{"type":"Feature","properties":{"ZIP":"P2A3B3","VERTICES":5},"geometry":{"type":"Point","coordinates":[-80.02246550000001,45.3466545]}},{"type":"Feature","properties":{"ZIP":"P2A1B1","VERTICES":5},"geometry":{"type":"Point","coordinates":[-80.03198499999999,45.343449]}},{"type":"Feature","properties":{"ZIP":"P2A1K2","VERTICES":5},"geometry":{"type":"Point","coordinates":[-80.037489,45.352425]}},{"type":"Feature","properties":{"ZIP":"P2A2X2","VERTICES":5},"geometry":{"type":"Point","coordinates":[-80.042644,45.345729500000004]}},{"type":"Feature","properties":{"ZIP":"P2A1C6","VERTICES":5},"geometry":{"type":"Point","coordinates":[-80.045166,45.348669]}},{"type":"Feature","properties":{"ZIP":"P2A1H6","VERTICES":5},"geometry":{"type":"Point","coordinates":[-80.0404785,45.351054]}},{"type":"Feature","properties":{"ZIP":"P2A2G6","VERTICES":5},"geometry":{"type":"Point","coordinates":[-80.03325849999999,45.3511265]}},{"type":"Feature","properties":{"ZIP":"P2A2V7","VERTICES":5},"geometry":{"type":"Point","coordinates":[-80.0241015,45.3456505]}},{"type":"Feature","properties":{"ZIP":"P2A1R3","VERTICES":5},"geometry":{"type":"Point","coordinates":[-80.0312115,45.356798999999995]}},{"type":"Feature","properties":{"ZIP":"P2A2X3","VERTICES":5},"geometry":{"type":"Point","coordinates":[-80.0386485,45.3191845]}},{"type":"Feature","properties":{"ZIP":"P2A1C7","VERTICES":5},"geometry":{"type":"Point","coordinates":[-80.0450045,45.348833]}},{"type":"Feature","properties":{"ZIP":"P2A2S8","VERTICES":5},"geometry":{"type":"Point","coordinates":[-80.015798,45.345197]}},{"type":"Feature","properties":{"ZIP":"P2A2Z5","VERTICES":5},"geometry":{"type":"Point","coordinates":[-80.0440315,45.352594499999995]}},{"type":"Feature","properties":{"ZIP":"P2A1V8","VERTICES":5},"geometry":{"type":"Point","coordinates":[-80.023309,45.3543705]}},{"type":"Feature","properties":{"ZIP":"P2A2V9","VERTICES":5},"geometry":{"type":"Point","coordinates":[-80.0225585,45.3442955]}},{"type":"Feature","properties":{"ZIP":"P2A3B9","VERTICES":5},"geometry":{"type":"Point","coordinates":[-80.0218105,45.348723]}},{"type":"Feature","properties":{"ZIP":"P2A1B4","VERTICES":5},"geometry":{"type":"Point","coordinates":[-80.027018,45.3498915]}},{"type":"Feature","properties":{"ZIP":"P2A1R7","VERTICES":5},"geometry":{"type":"Point","coordinates":[-80.039855,45.3537295]}},{"type":"Feature","properties":{"ZIP":"P2A2B8","VERTICES":5},"geometry":{"type":"Point","coordinates":[-80.041259,45.347747]}},{"type":"Feature","properties":{"ZIP":"P2A1M3","VERTICES":5},"geometry":{"type":"Point","coordinates":[-80.026159,45.35656]}},{"type":"Feature","properties":{"ZIP":"P2A2S9","VERTICES":5},"geometry":{"type":"Point","coordinates":[-80.015728,45.344969000000006]}},{"type":"Feature","properties":{"ZIP":"P2A1V9","VERTICES":5},"geometry":{"type":"Point","coordinates":[-80.0218005,45.355633999999995]}},{"type":"Feature","properties":{"ZIP":"P2A2G9","VERTICES":5},"geometry":{"type":"Point","coordinates":[-80.0332005,45.354122000000004]}},{"type":"Feature","properties":{"ZIP":"P2A1B7","VERTICES":5},"geometry":{"type":"Point","coordinates":[-80.038586,45.3444205]}},{"type":"Feature","properties":{"ZIP":"P2A1K6","VERTICES":5},"geometry":{"type":"Point","coordinates":[-80.026404,45.351394]}},{"type":"Feature","properties":{"ZIP":"P2A1R9","VERTICES":5},"geometry":{"type":"Point","coordinates":[-80.04082500000001,45.3534785]}},{"type":"Feature","properties":{"ZIP":"P2A2B9","VERTICES":5},"geometry":{"type":"Point","coordinates":[-80.041316,45.3485305]}},{"type":"Feature","properties":{"ZIP":"P2A2J2","VERTICES":5},"geometry":{"type":"Point","coordinates":[-80.02428649999999,45.3574795]}},{"type":"Feature","properties":{"ZIP":"P2A1E4","VERTICES":5},"geometry":{"type":"Point","coordinates":[-80.03578949999999,45.345623]}},{"type":"Feature","properties":{"ZIP":"P2A2L3","VERTICES":5},"geometry":{"type":"Point","coordinates":[-80.020122,45.342969499999995]}},{"type":"Feature","properties":{"ZIP":"P2A1W2","VERTICES":5},"geometry":{"type":"Point","coordinates":[-80.01983849999999,45.359319]}},{"type":"Feature","properties":{"ZIP":"P2A2W2","VERTICES":5},"geometry":{"type":"Point","coordinates":[-80.02196699999999,45.3454825]}},{"type":"Feature","properties":{"ZIP":"P2A2X7","VERTICES":4},"geometry":{"type":"Point","coordinates":[-80.03993750000001,45.344215]}},{"type":"Feature","properties":{"ZIP":"P2A0B6","VERTICES":4},"geometry":{"type":"Point","coordinates":[-79.7613085,45.382855]}},{"type":"Feature","properties":{"ZIP":"P2A2H2","VERTICES":4},"geometry":{"type":"Point","coordinates":[-80.029094,45.353077]}},{"type":"Feature","properties":{"ZIP":"P2A1L1","VERTICES":4},"geometry":{"type":"Point","coordinates":[-80.024254,45.353393]}},{"type":"Feature","properties":{"ZIP":"P2A1G2","VERTICES":4},"geometry":{"type":"Point","coordinates":[-80.03440499999999,45.348038]}},{"type":"Feature","properties":{"ZIP":"P2A2W6","VERTICES":4},"geometry":{"type":"Point","coordinates":[-80.0184195,45.345303]}},{"type":"Feature","properties":{"ZIP":"P2A1A4","VERTICES":4},"geometry":{"type":"Point","coordinates":[-80.03797850000001,45.3402995]}},{"type":"Feature","properties":{"ZIP":"P2A3A9","VERTICES":4},"geometry":{"type":"Point","coordinates":[-80.04162500000001,45.360451499999996]}},{"type":"Feature","properties":{"ZIP":"P2A2Z1","VERTICES":4},"geometry":{"type":"Point","coordinates":[-80.0314185,45.343072]}},{"type":"Feature","properties":{"ZIP":"P2A0A3","VERTICES":4},"geometry":{"type":"Point","coordinates":[-80.04496449999999,45.3478475]}},{"type":"Feature","properties":{"ZIP":"P2A1V5","VERTICES":4},"geometry":{"type":"Point","coordinates":[-80.025395,45.353086000000005]}},{"type":"Feature","properties":{"ZIP":"P2A0A6","VERTICES":4},"geometry":{"type":"Point","coordinates":[-80.0388615,45.3504385]}},{"type":"Feature","properties":{"ZIP":"P2A3B7","VERTICES":4},"geometry":{"type":"Point","coordinates":[-80.010406,45.34373]}},{"type":"Feature","properties":{"ZIP":"P2A0B2","VERTICES":4},"geometry":{"type":"Point","coordinates":[-79.8932355,45.297239000000005]}},{"type":"Feature","properties":{"ZIP":"P2A0B4","VERTICES":3},"geometry":{"type":"Point","coordinates":[-79.8853405,45.4969125]}},{"type":"Feature","properties":{"ZIP":"P2A2X5","VERTICES":3},"geometry":{"type":"Point","coordinates":[-80.02756500000001,45.3351675]}}]}