{"type":"FeatureCollection","features":[{"type":"Feature","properties":{"ZIP":"J0W1G0","VERTICES":14},"geometry":{"type":"Point","coordinates":[-75.3222015,46.484524]}},{"type":"Feature","properties":{"ZIP":"J0W1H0","VERTICES":14},"geometry":{"type":"Point","coordinates":[-75.3565855,46.537395000000004]}},{"type":"Feature","properties":{"ZIP":"J0W1P0","VERTICES":14},"geometry":{"type":"Point","coordinates":[-75.338165,46.784234]}},{"type":"Feature","properties":{"ZIP":"J0W1K0","VERTICES":12},"geometry":{"type":"Point","coordinates":[-75.32710449999999,46.714650500000005]}},{"type":"Feature","properties":{"ZIP":"J0W1A0","VERTICES":12},"geometry":{"type":"Point","coordinates":[-75.2314465,46.674223]}},{"type":"Feature","properties":{"ZIP":"J0W1R0","VERTICES":12},"geometry":{"type":"Point","coordinates":[-75.024112,46.409715]}},{"type":"Feature","properties":{"ZIP":"J0W1L0","VERTICES":11},"geometry":{"type":"Point","coordinates":[-75.126456,46.488304]}},{"type":"Feature","properties":{"ZIP":"J0W1E0","VERTICES":10},"geometry":{"type":"Point","coordinates":[-75.907448,46.616162]}},{"type":"Feature","properties":{"ZIP":"J0W1J0","VERTICES":9},"geometry":{"type":"Point","coordinates":[-75.529316,46.4031915]}},{"type":"Feature","properties":{"ZIP":"J0W1S0","VERTICES":9},"geometry":{"type":"Point","coordinates":[-75.49495999999999,46.3127735]}},{"type":"Feature","properties":{"ZIP":"J0W1N0","VERTICES":8},"geometry":{"type":"Point","coordinates":[-76.04250400000001,46.5699255]}},{"type":"Feature","properties":{"ZIP":"J0W1C0","VERTICES":7},"geometry":{"type":"Point","coordinates":[-75.4398865,46.684955]}},{"type":"Feature","properties":{"ZIP":"J0W1V0","VERTICES":7},"geometry":{"type":"Point","coordinates":[-75.3104805,46.8882105]}},{"type":"Feature","properties":{"ZIP":"J0W1W0","VERTICES":6},"geometry":{"type":"Point","coordinates":[-75.88569849999999,46.472429000000005]}},{"type":"Feature","properties":{"ZIP":"J0W1X0","VERTICES":6},"geometry":{"type":"Point","coordinates":[-74.9784645,46.550701000000004]}},{"type":"Feature","properties":{"ZIP":"J0W1B0","VERTICES":5},"geometry":{"type":"Point","coordinates":[-76.0201495,46.298297000000005]}},{"type":"Feature","properties":{"ZIP":"J0W1Y0","VERTICES":3},"geometry":{"type":"Point","coordinates":[-75.3754415,46.510564]}}]}